Workbook

Sheet for conversion
A1: account_no | B1: Name | C1: adjusted_gross_score | D1: slope_rating | E1: course_rating | F1: holes_completed | G1: date_played | H1: tee | I1: course | J1: tournament_name | K1: course_id | L1: tee_id | M1: whs_no
A2: 7524-03 | B2: JUNSAY, JARED JAMES | C2: 83 | D2: 134 | E2: 72.8 | F2: 18 | G2: 45888 | H2: B | I2: SOUTH | J2: ALL JUNIORS 2025 | M2: =VLOOKUP(A2,Sheet1!$A$2:$H$1628,1,FALSE) -> 7524-03
A3: 7494-06 | B3: HERMOSA, GABRIEL | C3: 87 | D3: 134 | E3: 72.8 | F3: 18 | G3: 45888 | H3: B | I3: SOUTH | J3: ALL JUNIORS 2025 | M3: =VLOOKUP(A3,Sheet1!$A$2:$H$1628,1,FALSE) -> 7494-06
A4: 8493-02 | B4: RAMOS, GAB | C4: 90 | D4: 134 | E4: 72.8 | F4: 18 | G4: 45888 | H4: B | I4: SOUTH | J4: ALL JUNIORS 2025 | M4: =VLOOKUP(A4,Sheet1!$A$2:$H$1628,1,FALSE) -> 8493-02
A5: 7783-02 | B5: BAYANI, CLARK | C5: 99 | D5: 134 | E5: 72.8 | F5: 18 | G5: 45888 | H5: B | I5: SOUTH | J5: ALL JUNIORS 2025 | M5: =VLOOKUP(A5,Sheet1!$A$2:$H$1628,1,FALSE) -> 7783-02
A6: 3243-02 | B6: CRUZ, CHRISTOPHER ANDREI | C6: 103 | D6: 134 | E6: 72.8 | F6: 18 | G6: 45888 | H6: B | I6: SOUTH | J6: ALL JUNIORS 2025 | M6: =VLOOKUP(A6,Sheet1!$A$2:$H$1628,1,FALSE) -> 3243-02
A7: 8225-03 | B7: NICOLAS, RYAN JR. | C7: 95 | D7: 134 | E7: 72.8 | F7: 18 | G7: 45888 | H7: B | I7: SOUTH | J7: ALL JUNIORS 2025 | M7: =VLOOKUP(A7,Sheet1!$A$2:$H$1628,1,FALSE) -> 8225-03
A8: 8356-02 | B8: LIMPIADA, ZIAN JAMES | C8: 96 | D8: 134 | E8: 72.8 | F8: 18 | G8: 45888 | H8: B | I8: SOUTH | J8: ALL JUNIORS 2025 | M8: =VLOOKUP(A8,Sheet1!$A$2:$H$1628,1,FALSE) -> 8356-02
A9: 3243-03 | B9: CRUZ, AIDEN CHRISTOPHER | C9: 105 | D9: 134 | E9: 72.8 | F9: 18 | G9: 45888 | H9: B | I9: SOUTH | J9: ALL JUNIORS 2025 | M9: =VLOOKUP(A9,Sheet1!$A$2:$H$1628,1,FALSE) -> 3243-03
A10: 3634-02 | B10: VEA, LIAM MARCUS | C10: 105 | D10: 134 | E10: 72.8 | F10: 18 | G10: 45888 | H10: B | I10: SOUTH | J10: ALL JUNIORS 2025 | M10: =VLOOKUP(A10,Sheet1!$A$2:$H$1628,1,FALSE) -> 3634-02
A11: 2963-02 | B11: IÑIGO, MIGUEL | C11: 116 | D11: 134 | E11: 72.8 | F11: 18 | G11: 45888 | H11: B | I11: SOUTH | J11: ALL JUNIORS 2025 | M11: =VLOOKUP(A11,Sheet1!$A$2:$H$1628,1,FALSE) -> 2963-02
A12: 2606-04 | B12: MANHIT, RACE PHOENIX YATCO | C12: 80 | D12: 134 | E12: 72.8 | F12: 18 | G12: 45888 | H12: B | I12: SOUTH | J12: ALL JUNIORS 2025 | M12: =VLOOKUP(A12,Sheet1!$A$2:$H$1628,1,FALSE) -> 2606-04
A13: 3516-02 | B13: DAVID, PEIRRE XANDREI P. | C13: 81 | D13: 134 | E13: 72.8 | F13: 18 | G13: 45888 | H13: B | I13: SOUTH | J13: ALL JUNIORS 2025 | M13: =VLOOKUP(A13,Sheet1!$A$2:$H$1628,1,FALSE) -> 3516-02
A14: 3562-02 | B14: UNGCO, ROMAN FRANCESCO | C14: 81 | D14: 134 | E14: 72.8 | F14: 18 | G14: 45888 | H14: B | I14: SOUTH | J14: ALL JUNIORS 2025 | M14: =VLOOKUP(A14,Sheet1!$A$2:$H$1628,1,FALSE) -> 3562-02
A15: 3575-02 | B15: DY SUN, ADAM JOSE GAVINO B. | C15: 60 | D15: 129 | E15: 73.3 | F15: B9 | G15: 45888 | H15: R | I15: SOUTH | J15: ALL JUNIORS 2025 | M15: =VLOOKUP(A15,Sheet1!$A$2:$H$1628,1,FALSE) -> 3575-02
A16: 8203-03 | B16: CHAN, AERIN LOUISE | C16: 82 | D16: 129 | E16: 73.3 | F16: 18 | G16: 45888 | H16: R | I16: SOUTH | J16: ALL JUNIORS 2025 | M16: =VLOOKUP(A16,Sheet1!$A$2:$H$1628,1,FALSE) -> 8203-03
A17: 1757-02 | B17: MAURICIO, ALEXANDRA | C17: 83 | D17: 129 | E17: 73.3 | F17: 18 | G17: 45888 | H17: R | I17: SOUTH | J17: ALL JUNIORS 2025 | M17: =VLOOKUP(A17,Sheet1!$A$2:$H$1628,1,FALSE) -> 1757-02
A18: 7874-04 | B18: NAMOCO, MARGAUX | C18: 87 | D18: 129 | E18: 73.3 | F18: 18 | G18: 45888 | H18: R | I18: SOUTH | J18: ALL JUNIORS 2025 | M18: =VLOOKUP(A18,Sheet1!$A$2:$H$1628,1,FALSE) -> 7874-04
A19: 8411-03 | B19: EUSEBIO, JESSICA VENICE | C19: 103 | D19: 129 | E19: 73.3 | F19: 18 | G19: 45888 | H19: R | I19: SOUTH | J19: ALL JUNIORS 2025 | M19: =VLOOKUP(A19,Sheet1!$A$2:$H$1628,1,FALSE) -> 8411-03
A20: 8455-03 | B20: YAZON, MATTEO | C20: 111 | D20: 126 | E20: 70.6 | F20: 18 | G20: 45888 | H20: W | I20: SOUTH | J20: ALL JUNIORS 2025 | M20: =VLOOKUP(A20,Sheet1!$A$2:$H$1628,1,FALSE) -> 8455-03
A21: 8278-03 | B21: FERNANDO, JESUS III | C21: 112 | D21: 126 | E21: 70.6 | F21: 18 | G21: 45888 | H21: W | I21: SOUTH | J21: ALL JUNIORS 2025 | M21: =VLOOKUP(A21,Sheet1!$A$2:$H$1628,1,FALSE) -> 8278-03
A22: 8278-04 | B22: FERNANDO, JUAN JAVIER | C22: 116 | D22: 126 | E22: 70.6 | F22: 18 | G22: 45888 | H22: W | I22: SOUTH | J22: ALL JUNIORS 2025 | M22: =VLOOKUP(A22,Sheet1!$A$2:$H$1628,1,FALSE) -> 8278-04
A23: 8411-02 | B23: EUSEBIO, JENINA SYDNEY | C23: 97 | D23: 126 | E23: 70.6 | F23: 18 | G23: 45888 | H23: W | I23: SOUTH | J23: ALL JUNIORS 2025 | M23: =VLOOKUP(A23,Sheet1!$A$2:$H$1628,1,FALSE) -> 8411-02
A24: 8520-02 | B24: BAUTISTA, FRANCES CATE | C24: 97 | D24: 126 | E24: 70.6 | F24: 18 | G24: 45888 | H24: W | I24: SOUTH | J24: ALL JUNIORS 2025 | M24: =VLOOKUP(A24,Sheet1!$A$2:$H$1628,1,FALSE) -> 8520-02
A25: 7783-03 | B25: BAYANI, FELINA | C25: 112 | D25: 126 | E25: 70.6 | F25: 18 | G25: 45888 | H25: W | I25: SOUTH | J25: ALL JUNIORS 2025 | M25: =VLOOKUP(A25,Sheet1!$A$2:$H$1628,1,FALSE) -> 7783-03
A26: 2963-03 | B26: IÑIGO, MARTINA | C26: 118 | D26: 126 | E26: 70.6 | F26: 18 | G26: 45888 | H26: W | I26: SOUTH | J26: ALL JUNIORS 2025 | M26: =VLOOKUP(A26,Sheet1!$A$2:$H$1628,1,FALSE) -> 2963-03
A27: 8109-02 | B27: CAMPOSANO, INIGO | C27: 97 | D27: 126 | E27: 70.6 | F27: 18 | G27: 45888 | H27: W | I27: SOUTH | J27: ALL JUNIORS 2025 | M27: =VLOOKUP(A27,Sheet1!$A$2:$H$1628,1,FALSE) -> 8109-02
... A237: 2981-00 | B237: FAJARDO, MARLON | C237: 88 | D237: 123 | E237: 66.5 | F237: 18 | G237: 45507 | H237: W | I237: NORTH | J237: BARKADAHAN 2024 | M237: =VLOOKUP(A237,Sheet1!$A$2:$H$1628,1,FALSE) -> 2981-00
A238: 3137-00 | B238: GOROSPE, BEN | D238: 123 | E238: 66.5 | F238: 18 | G238: 45479 | H238: W | I238: NORTH | J238: BARKADAHAN 2024 | M238: =VLOOKUP(A238,Sheet1!$A$2:$H$1628,1,FALSE) -> 3137-00
A239: 1073-00 | B239: JORGE, RAOUL | C239: 74 | D239: 123 | E239: 66.5 | F239: 18 | G239: 45495 | H239: W | I239: NORTH | J239: BARKADAHAN 2024 | M239: =VLOOKUP(A239,Sheet1!$A$2:$H$1628,1,FALSE) -> 1073-00
A240: 1016-00 | B240: SAN JUAN, JOSE ERWIN | C240: 78 | D240: 123 | E240: 66.5 | F240: 18 | G240: 45508 | H240: W | I240: NORTH | J240: BARKADAHAN 2024 | M240: =VLOOKUP(A240,Sheet1!$A$2:$H$1628,1,FALSE) -> 1016-00
A241: 7971-00 | B241: SOMERA, RANDOLF | C241: 87 | D241: 123 | E241: 66.5 | F241: 18 | G241: 45465 | H241: W | I241: NORTH | J241: BARKADAHAN 2024 | M241: =VLOOKUP(A241,Sheet1!$A$2:$H$1628,1,FALSE) -> 7971-00
A242: 3330-00 | B242: SUMULONG, FRANCISCO | C242: 73 | D242: 123 | E242: 66.5 | F242: 18 | G242: 45508 | H242: W | I242: NORTH | J242: BARKADAHAN 2024 | M242: =VLOOKUP(A242,Sheet1!$A$2:$H$1628,1,FALSE) -> 3330-00
A243: 7288-00 | B243: VILALLON, VINCENT | C243: 83 | D243: 123 | E243: 66.5 | F243: 18 | G243: 45479 | H243: W | I243: NORTH | J243: BARKADAHAN 2024 | M243: =VLOOKUP(A243,Sheet1!$A$2:$H$1628,1,FALSE) -> 7288-00
A244: 7931-00 | B244: CASTILLO, GEORGE PATRICK | C244: 96 | D244: 135 | E244: 72 | F244: 18 | G244: 45487 | H244: B | I244: SOUTH | J244: BARKADAHAN 2024 | M244: =VLOOKUP(A244,Sheet1!$A$2:$H$1628,1,FALSE) -> 7931-00
A245: 8450-01 | B245: DATOC, RJ | C245: 88 | D245: 135 | E245: 72 | F245: 18 | G245: 45465 | H245: B | I245: SOUTH | J245: BARKADAHAN 2024 | M245: =VLOOKUP(A245,Sheet1!$A$2:$H$1628,1,FALSE) -> 8450-01
A246: 2606-04 | B246: MANHIT, RACE | C246: 77 | D246: 135 | E246: 72 | F246: 18 | G246: 45465 | H246: B | I246: SOUTH | J246: BARKADAHAN 2024 | M246: =VLOOKUP(A246,Sheet1!$A$2:$H$1628,1,FALSE) -> 2606-04
A247: 8149-00 | B247: MONTER0, VINCE | C247: 88 | D247: 135 | E247: 72 | F247: 18 | G247: 45465 | H247: B | I247: SOUTH | J247: BARKADAHAN 2024 | M247: =VLOOKUP(A247,Sheet1!$A$2:$H$1628,1,FALSE) -> 8149-00
A248: 8287-00 | B248: RAZON, JOSE LUIS | C248: 83 | D248: 135 | E248: 72 | F248: 18 | G248: 45487 | H248: B | I248: SOUTH | J248: BARKADAHAN 2024 | M248: =VLOOKUP(A248,Sheet1!$A$2:$H$1628,1,FALSE) -> #N/A
A249: 2781-00 | B249: SARTE, ERNEST | C249: 85 | D249: 135 | E249: 72 | F249: 18 | G249: 45472 | H249: B | I249: SOUTH | J249: BARKADAHAN 2024 | M249: =VLOOKUP(A249,Sheet1!$A$2:$H$1628,1,FALSE) -> 2781-00
A250: 0187-01 | B250: CARLOS, ARSENIA M. | C250: 86 | D250: 131 | E250: 73.1 | F250: 18 | G250: 45479 | H250: R | I250: SOUTH | J250: BARKADAHAN 2024 | M250: =VLOOKUP(A250,Sheet1!$A$2:$H$1628,1,FALSE) -> 0187-01
... A265: 7288-00 | B265: VILLALON, VINCENT | C265: 85 | D265: 131 | E265: 70 | F265: 18 | G265: 45465 | H265: W | I265: SOUTH | J265: BARKADAHAN 2024 | M265: =VLOOKUP(A265,Sheet1!$A$2:$H$1628,1,FALSE) -> 7288-00
A266: 3403-00 | B266: ALEJANDRO, JEROU JOSE | C266: 45 | D266: 138 | E266: 34.9 | F266: F9 | G266: 45830 | H266: B | I266: NORTH | J266: BARKADAHAN 2025 | M266: =VLOOKUP(A266,Sheet1!$A$2:$H$1628,1,FALSE) -> 3403-00
A267: 7943-00 | B267: ALINO, CARLO EDUARDO | C267: 46 | D267: 138 | E267: 34.9 | F267: F9 | G267: 45830 | H267: B | I267: NORTH | J267: BARKADAHAN 2025 | M267: =VLOOKUP(A267,Sheet1!$A$2:$H$1628,1,FALSE) -> 7943-00
A268: 8282-00 | B268: ANDOYO, LEONEL | C268: 42 | D268: 138 | E268: 34.9 | F268: F9 | G268: 45822 | H268: B | I268: NORTH | J268: BARKADAHAN 2025 | M268: =VLOOKUP(A268,Sheet1!$A$2:$H$1628,1,FALSE) -> 8282-00
A269: 8282-00 | B269: ANDOYO, LEONEL | C269: 46 | D269: 138 | E269: 34.9 | F269: F9 | G269: 45809 | H269: B | I269: NORTH | J269: BARKADAHAN 2025 | M269: =VLOOKUP(A269,Sheet1!$A$2:$H$1628,1,FALSE) -> 8282-00
A270: 8552-00 | B270: ANGLUBEN, HAMILTON | C270: 54 | D270: 138 | E270: 34.9 | F270: F9 | G270: 45816 | H270: B | I270: NORTH | J270: BARKADAHAN 2025 | M270: =VLOOKUP(A270,Sheet1!$A$2:$H$1628,1,FALSE) -> 8552-00
A271: 8085-00 | B271: BASIT, LUISITO | C271: 47 | D271: 138 | E271: 34.9 | F271: F9 | G271: 45830 | H271: B | I271: NORTH | J271: BARKADAHAN 2025 | M271: =VLOOKUP(A271,Sheet1!$A$2:$H$1628,1,FALSE) -> 8085-00
A272: 3301-04 | B272: BAUTISTA, JAVIER STEFANO | C272: 37 | D272: 138 | E272: 34.9 | F272: F9 | G272: 45816 | H272: B | I272: NORTH | J272: BARKADAHAN 2025 | M272: =VLOOKUP(A272,Sheet1!$A$2:$H$1628,1,FALSE) -> 3301-04
A273: 2614-00 | B273: BENITEZ, TOMAS JULIO A. | C273: 37 | D273: 138 | E273: 34.9 | F273: F9 | G273: 45851 | H273: B | I273: NORTH | J273: BARKADAHAN 2025 | M273: =VLOOKUP(A273,Sheet1!$A$2:$H$1628,1,FALSE) -> 2614-00
A274: 2614-00 | B274: BENITEZ, TOMAS JULIO A. | C274: 37 | D274: 138 | E274: 34.9 | F274: F9 | G274: 45878 | H274: B | I274: NORTH | J274: BARKADAHAN 2025 | M274: =VLOOKUP(A274,Sheet1!$A$2:$H$1628,1,FALSE) -> 2614-00
A275: 8174-00 | B275: BERNARDO, JOSE RONALDO | C275: 39 | D275: 125 | E275: 33.9 | F275: B9 | G275: 45802 | H275: B | I275: NORTH | J275: BARKADAHAN 2025 | M275: =VLOOKUP(A275,Sheet1!$A$2:$H$1628,1,FALSE) -> 8174-00
A276: 8174-00 | B276: BERNARDO, JOSE RONALDO | C276: 75 | D276: 132 | E276: 68.8 | F276: 18 | G276: 45809 | H276: B | I276: NORTH | J276: BARKADAHAN 2025 | M276: =VLOOKUP(A276,Sheet1!$A$2:$H$1628,1,FALSE) -> 8174-00
A277: 8304-00 | B277: BILBAO, JOAQUIN VICENTE | C277: 50 | D277: 138 | E277: 34.9 | F277: F9 | G277: 45822 | H277: B | I277: NORTH | J277: BARKADAHAN 2025 | M277: =VLOOKUP(A277,Sheet1!$A$2:$H$1628,1,FALSE) -> 8304-00
A278: 8106-00 | B278: BONIFACIO, ROGELIO JR. | C278: 43 | D278: 138 | E278: 34.9 | F278: F9 | G278: 45809 | H278: B | I278: NORTH | J278: BARKADAHAN 2025 | M278: =VLOOKUP(A278,Sheet1!$A$2:$H$1628,1,FALSE) -> 8106-00
A279: 8106-00 | B279: BONIFACIO, ROGELIO JR. | C279: 53 | D279: 138 | E279: 34.9 | F279: F9 | G279: 45802 | H279: B | I279: NORTH | J279: BARKADAHAN 2025 | M279: =VLOOKUP(A279,Sheet1!$A$2:$H$1628,1,FALSE) -> 8106-00
A280: 8208-00 | B280: BORLADO, ERNESTO | C280: 41 | D280: 138 | E280: 34.9 | F280: F9 | G280: 45851 | H280: B | I280: NORTH | J280: BARKADAHAN 2025 | M280: =VLOOKUP(A280,Sheet1!$A$2:$H$1628,1,FALSE) -> 8208-00
A281: 1058-00 | B281: CAPARROS, MARVIN A. | C281: 48 | D281: 138 | E281: 34.9 | F281: F9 | G281: 45815 | H281: B | I281: NORTH | J281: BARKADAHAN 2025 | M281: =VLOOKUP(A281,Sheet1!$A$2:$H$1628,1,FALSE) -> 1058-00
A282: 8357-00 | B282: CASIMIRO, KENNETH | C282: 80 | D282: 132 | E282: 68.8 | F282: 18 | G282: 45802 | H282: B | I282: NORTH | J282: BARKADAHAN 2025 | M282: =VLOOKUP(A282,Sheet1!$A$2:$H$1628,1,FALSE) -> 8357-00
A283: 2737-00 | B283: CEMBRANO, MICHAEL ANTHONY | C283: 95 | D283: 132 | E283: 68.8 | F283: 18 | G283: 45802 | H283: B | I283: NORTH | J283: BARKADAHAN 2025 | M283: =VLOOKUP(A283,Sheet1!$A$2:$H$1628,1,FALSE) -> 2737-00
A284: 8259-00 | B284: CHANCO, GUILLERMO | C284: 50 | D284: 138 | E284: 34.9 | F284: F9 | G284: 45808 | H284: B | I284: NORTH | J284: BARKADAHAN 2025 | M284: =VLOOKUP(A284,Sheet1!$A$2:$H$1628,1,FALSE) -> 8259-00
A285: 8214-00 | B285: CHUA, HECTOR | C285: 45 | D285: 138 | E285: 34.9 | F285: F9 | G285: 45837 | H285: B | I285: NORTH | J285: BARKADAHAN 2025 | M285: =VLOOKUP(A285,Sheet1!$A$2:$H$1628,1,FALSE) -> 8214-00
A286: 1260-00 | B286: CHUA, HOWARD O. | C286: 41 | D286: 138 | E286: 34.9 | F286: F9 | G286: 45809 | H286: B | I286: NORTH | J286: BARKADAHAN 2025 | M286: =VLOOKUP(A286,Sheet1!$A$2:$H$1628,1,FALSE) -> 1260-00
A287: 8214-02 | B287: CHUA, JACOB | C287: 35 | D287: 138 | E287: 34.9 | F287: F9 | G287: 45837 | H287: B | I287: NORTH | J287: BARKADAHAN 2025 | M287: =VLOOKUP(A287,Sheet1!$A$2:$H$1628,1,FALSE) -> 8214-02
A288: 3210-00 | B288: CHUNG, GIAN GABRIEL | C288: 37 | D288: 138 | E288: 34.9 | F288: F9 | G288: 45822 | H288: B | I288: NORTH | J288: BARKADAHAN 2025 | M288: =VLOOKUP(A288,Sheet1!$A$2:$H$1628,1,FALSE) -> 3210-00
A289: 8500-00 | B289: CHUNG, GIAN TIMOTHY | C289: 39 | D289: 138 | E289: 34.9 | F289: F9 | G289: 45836 | H289: B | I289: NORTH | J289: BARKADAHAN 2025 | M289: =VLOOKUP(A289,Sheet1!$A$2:$H$1628,1,FALSE) -> 8500-00
A290: 3243-02 | B290: CRUZ, ANDREI | C290: 44 | D290: 138 | E290: 34.9 | F290: F9 | G290: 45829 | H290: B | I290: NORTH | J290: BARKADAHAN 2025 | M290: =VLOOKUP(A290,Sheet1!$A$2:$H$1628,1,FALSE) -> 3243-02
A291: 8407-02 | B291: CURRAN, EMILIO | C291: 38 | D291: 138 | E291: 34.9 | F291: F9 | G291: 45837 | H291: B | I291: NORTH | J291: BARKADAHAN 2025 | M291: =VLOOKUP(A291,Sheet1!$A$2:$H$1628,1,FALSE) -> 8407-02
A292: 3021-00 | B292: DARJUAN, ANTONIO JR. | C292: 47 | D292: 138 | E292: 34.9 | F292: F9 | G292: 45808 | H292: B | I292: NORTH | J292: BARKADAHAN 2025 | M292: =VLOOKUP(A292,Sheet1!$A$2:$H$1628,1,FALSE) -> 3021-00
A293: 8450-01 | B293: DATOC, RJ | C293: 42 | D293: 138 | E293: 34.9 | F293: F9 | G293: 45851 | H293: B | I293: NORTH | J293: BARKADAHAN 2025 | M293: =VLOOKUP(A293,Sheet1!$A$2:$H$1628,1,FALSE) -> 8450-01
A294: 3377-00 | B294: DAVID, CARLOS PRIMO | C294: 86 | D294: 132 | E294: 68.8 | F294: 18 | G294: 45871 | H294: B | I294: NORTH | J294: BARKADAHAN 2025 | M294: =VLOOKUP(A294,Sheet1!$A$2:$H$1628,1,FALSE) -> 3377-00
A295: 3516-02 | B295: DAVID, PIERRE XANDREI | C295: 36 | D295: 138 | E295: 34.9 | F295: F9 | G295: 45843 | H295: B | I295: NORTH | J295: BARKADAHAN 2025 | M295: =VLOOKUP(A295,Sheet1!$A$2:$H$1628,1,FALSE) -> 3516-02
A296: 3516-02 | B296: DAVID, PIERRE XANDREI | C296: 41 | D296: 138 | E296: 34.9 | F296: F9 | G296: 45815 | H296: B | I296: NORTH | J296: BARKADAHAN 2025 | M296: =VLOOKUP(A296,Sheet1!$A$2:$H$1628,1,FALSE) -> 3516-02
A297: 3516-02 | B297: DAVID, PIERRE XANDREI | C297: 43 | D297: 138 | E297: 34.9 | F297: F9 | G297: 45829 | H297: B | I297: NORTH | J297: BARKADAHAN 2025 | M297: =VLOOKUP(A297,Sheet1!$A$2:$H$1628,1,FALSE) -> 3516-02
A298: 3516-02 | B298: DAVID, PIERRE XANDREI | C298: 46 | D298: 138 | E298: 34.9 | F298: F9 | G298: 45802 | H298: B | I298: NORTH | J298: BARKADAHAN 2025 | M298: =VLOOKUP(A298,Sheet1!$A$2:$H$1628,1,FALSE) -> 3516-02
A299: 3218-00 | B299: DE LEON, DANTE | C299: 46 | D299: 138 | E299: 34.9 | F299: F9 | G299: 45808 | H299: B | I299: NORTH | J299: BARKADAHAN 2025 | M299: =VLOOKUP(A299,Sheet1!$A$2:$H$1628,1,FALSE) -> 3218-00
A300: 3426-00 | B300: DE LEON, JOSEPH ANTHONY | C300: 43 | D300: 138 | E300: 34.9 | F300: F9 | G300: 45802 | H300: B | I300: NORTH | J300: BARKADAHAN 2025 | M300: =VLOOKUP(A300,Sheet1!$A$2:$H$1628,1,FALSE) -> 3426-00
A301: 3426-00 | B301: DE LEON, JOSEPH ANTHONY | C301: 45 | D301: 138 | E301: 34.9 | F301: F9 | G301: 45809 | H301: B | I301: NORTH | J301: BARKADAHAN 2025 | M301: =VLOOKUP(A301,Sheet1!$A$2:$H$1628,1,FALSE) -> 3426-00
A302: 3167-00 | B302: DIAZ, EDISON | C302: 46 | D302: 138 | E302: 34.9 | F302: F9 | G302: 45878 | H302: B | I302: NORTH | J302: BARKADAHAN 2025 | M302: =VLOOKUP(A302,Sheet1!$A$2:$H$1628,1,FALSE) -> 3167-00
A303: 3167-00 | B303: DIAZ, EDISON | C303: 51 | D303: 138 | E303: 34.9 | F303: F9 | G303: 45815 | H303: B | I303: NORTH | J303: BARKADAHAN 2025 | M303: =VLOOKUP(A303,Sheet1!$A$2:$H$1628,1,FALSE) -> 3167-00
A304: 7571-00 | B304: DIMACULANGAN, ERWIN | C304: 47 | D304: 138 | E304: 34.9 | F304: F9 | G304: 45822 | H304: B | I304: NORTH | J304: BARKADAHAN 2025 | M304: =VLOOKUP(A304,Sheet1!$A$2:$H$1628,1,FALSE) -> 7571-00
A305: 7840-00 | B305: DIOKNO, JONATHAN | C305: 93 | D305: 132 | E305: 68.8 | F305: 18 | G305: 45829 | H305: B | I305: NORTH | J305: BARKADAHAN 2025 | M305: =VLOOKUP(A305,Sheet1!$A$2:$H$1628,1,FALSE) -> 7840-00
A306: 3024-00 | B306: DIZON, ANGEL RICARDO | C306: 41 | D306: 138 | E306: 34.9 | F306: F9 | G306: 45822 | H306: B | I306: NORTH | J306: BARKADAHAN 2025 | M306: =VLOOKUP(A306,Sheet1!$A$2:$H$1628,1,FALSE) -> 3024-00
A307: 3024-00 | B307: DIZON, ANGEL RICARDO | C307: 47 | D307: 138 | E307: 34.9 | F307: F9 | G307: 45871 | H307: B | I307: NORTH | J307: BARKADAHAN 2025 | M307: =VLOOKUP(A307,Sheet1!$A$2:$H$1628,1,FALSE) -> 3024-00
A308: 8441-00 | B308: DIZON, RAMON MIGUEL JR. | C308: 41 | D308: 138 | E308: 34.9 | F308: F9 | G308: 45808 | H308: B | I308: NORTH | J308: BARKADAHAN 2025 | M308: =VLOOKUP(A308,Sheet1!$A$2:$H$1628,1,FALSE) -> 8441-00
A309: 8441-00 | B309: DIZON, RAMON MIGUEL JR. | C309: 43 | D309: 138 | E309: 34.9 | F309: F9 | G309: 45878 | H309: B | I309: NORTH | J309: BARKADAHAN 2025 | M309: =VLOOKUP(A309,Sheet1!$A$2:$H$1628,1,FALSE) -> 8441-00
A310: 8330-00 | B310: ESGUERRA, DENNIS AUGUSTIN | C310: 50 | D310: 138 | E310: 34.9 | F310: F9 | G310: 45830 | H310: B | I310: NORTH | J310: BARKADAHAN 2025 | M310: =VLOOKUP(A310,Sheet1!$A$2:$H$1628,1,FALSE) -> 8330-00
A311: 8406-00 | B311: ESTRELLA, EMMANUEL | C311: 89 | D311: 132 | E311: 68.8 | F311: 18 | G311: 45809 | H311: B | I311: NORTH | J311: BARKADAHAN 2025 | M311: =VLOOKUP(A311,Sheet1!$A$2:$H$1628,1,FALSE) -> 8406-00
A312: 8406-00 | B312: ESTRELLA, EMMANUEL | C312: 81 | D312: 132 | E312: 68.8 | F312: 18 | G312: 45836 | H312: B | I312: NORTH | J312: BARKADAHAN 2025 | M312: =VLOOKUP(A312,Sheet1!$A$2:$H$1628,1,FALSE) -> 8406-00
A313: 2735-00 | B313: FELICIANO, LAWRENCE | C313: 51 | D313: 138 | E313: 34.9 | F313: F9 | G313: 45808 | H313: B | I313: NORTH | J313: BARKADAHAN 2025 | M313: =VLOOKUP(A313,Sheet1!$A$2:$H$1628,1,FALSE) -> 2735-00
A314: 3336-00 | B314: FELICIANO, RICO | C314: 41 | D314: 138 | E314: 34.9 | F314: F9 | G314: 45822 | H314: B | I314: NORTH | J314: BARKADAHAN 2025 | M314: =VLOOKUP(A314,Sheet1!$A$2:$H$1628,1,FALSE) -> 3336-00
A315: 3276-01 | B315: FREGIL, JERE | C315: 39 | D315: 138 | E315: 34.9 | F315: F9 | G315: 45815 | H315: B | I315: NORTH | J315: BARKADAHAN 2025 | M315: =VLOOKUP(A315,Sheet1!$A$2:$H$1628,1,FALSE) -> 3276-01
A316: 3276-01 | B316: FREGIL, JERE | C316: 43 | D316: 138 | E316: 34.9 | F316: F9 | G316: 45871 | H316: B | I316: NORTH | J316: BARKADAHAN 2025 | M316: =VLOOKUP(A316,Sheet1!$A$2:$H$1628,1,FALSE) -> 3276-01
A317: 3119-00 | B317: GABRIEL, BOBBY | C317: 46 | D317: 138 | E317: 34.9 | F317: F9 | G317: 45851 | H317: B | I317: NORTH | J317: BARKADAHAN 2025 | M317: =VLOOKUP(A317,Sheet1!$A$2:$H$1628,1,FALSE) -> 3119-00
A318: 8505-00 | B318: GO, EDWARD | C318: 47 | D318: 138 | E318: 34.9 | F318: F9 | G318: 45836 | H318: B | I318: NORTH | J318: BARKADAHAN 2025 | M318: =VLOOKUP(A318,Sheet1!$A$2:$H$1628,1,FALSE) -> 8505-00
A319: 7802-00 | B319: GO, RUDOLPH | C319: 50 | D319: 138 | E319: 34.9 | F319: F9 | G319: 45837 | H319: B | I319: NORTH | J319: BARKADAHAN 2025 | M319: =VLOOKUP(A319,Sheet1!$A$2:$H$1628,1,FALSE) -> 7802-00
A320: 3297-00 | B320: GONZALES, LEOJUN | C320: 41 | D320: 138 | E320: 34.9 | F320: F9 | G320: 45830 | H320: B | I320: NORTH | J320: BARKADAHAN 2025 | M320: =VLOOKUP(A320,Sheet1!$A$2:$H$1628,1,FALSE) -> 3297-00
A321: 8185-00 | B321: GUINTU, JULIENNE MARI | C321: 43 | D321: 125 | E321: 33.9 | F321: B9 | G321: 45802 | H321: B | I321: NORTH | J321: BARKADAHAN 2025 | M321: =VLOOKUP(A321,Sheet1!$A$2:$H$1628,1,FALSE) -> 8185-00
A322: 3069-00 | B322: HERRERA, JUAN PAOLO | C322: 41 | D322: 138 | E322: 34.9 | F322: F9 | G322: 45837 | H322: B | I322: NORTH | J322: BARKADAHAN 2025 | M322: =VLOOKUP(A322,Sheet1!$A$2:$H$1628,1,FALSE) -> 3069-00
A323: 2963-00 | B323: IÑIGO, MARCOS PAOLO | C323: 48 | D323: 138 | E323: 34.9 | F323: F9 | G323: 45816 | H323: B | I323: NORTH | J323: BARKADAHAN 2025 | M323: =VLOOKUP(A323,Sheet1!$A$2:$H$1628,1,FALSE) -> 2963-00
...

Sheet orig
A1: account_no | B1: Name | C1: adjusted_gross_score | D1: slope_rating | E1: course_rating | F1: holes_completed | G1: date_played | H1: tee | I1: course | J1: tournament_name | K1: course_id | L1: tee_id | M1: whs_no
A2: 2770-00 | B2: ABAD, RAMON MICHAEL | C2: 97 | D2: 126 | E2: 70.6 | F2: 18 | G2: 45899 | H2: W | I2: SOUTH | J2: All Seniors 2025 | M2: =VLOOKUP(A2,#REF!,5,FALSE) -> #REF!
A3: 2770-00 | B3: ABAD, RAMON MICHAEL | C3: 93 | D3: 125 | E3: 66.7 | F3: 18 | G3: 45914 | H3: W | I3: NORTH | J3: PRESCUP 2025 | M3: =VLOOKUP(A3,#REF!,5,FALSE) -> #REF!
A4: 2770-00 | B4: ABAD, RAMON MICHAEL | C4: 95 | D4: 126 | E4: 70.6 | F4: 18 | G4: 45550 | H4: W | I4: SOUTH | J4: PRESCUP 2024 | M4: =VLOOKUP(A4,#REF!,5,FALSE) -> #REF!
A5: 2770-00 | B5: ABAD, RAMON MICHAEL | C5: 98 | D5: 126 | E5: 70.6 | F5: 18 | G5: 45577 | H5: W | I5: SOUTH | J5: CLUB CHAMP Q1 2025 | M5: =VLOOKUP(A5,#REF!,5,FALSE) -> #REF!
A6: 2770-00 | B6: ABAD, RAMON MICHAEL | C6: 104 | D6: 126 | E6: 70.6 | F6: 18 | G6: 45297 | H6: W | I6: SOUTH | J6: CLUB CHAMP Q1 2024 | M6: =VLOOKUP(A6,#REF!,5,FALSE) -> #REF!
A7: 2770-00 | B7: ABAD, RAMON MICHAEL | C7: 49 | D7: 132 | E7: 36.2 | F7: B9 | G7: 45802 | H7: B | I7: SOUTH | J7: BARKADAHAN 2025 | M7: =VLOOKUP(A7,#REF!,5,FALSE) -> #REF!
A8: 2870-00 | B8: ABALOS, HILARIO O | C8: 76 | D8: 125 | E8: 66.7 | F8: 18 | G8: 45899 | H8: W | I8: NORTH | J8: All Seniors 2025 | M8: =VLOOKUP(A8,#REF!,5,FALSE) -> #REF!
A9: 2870-00 | B9: ABALOS, HILARIO O | C9: 97 | D9: 125 | E9: 66.7 | F9: 18 | G9: 45914 | H9: W | I9: NORTH | J9: PRESCUP 2025 | M9: =VLOOKUP(A9,#REF!,5,FALSE) -> #REF!
A10: 2870-00 | B10: ABALOS, HILARIO O | C10: 82 | D10: 125 | E10: 66.7 | F10: 18 | G10: 45550 | H10: W | I10: NORTH | J10: PRESCUP 2024 | M10: =VLOOKUP(A10,#REF!,5,FALSE) -> #REF!
A11: 2870-00 | B11: ABALOS, HILARIO O | C11: 93 | D11: 126 | E11: 70.6 | F11: 18 | G11: 45774 | H11: W | I11: SOUTH | J11: INTRA 2025 | M11: =VLOOKUP(A11,#REF!,5,FALSE) -> #REF!
A12: 2870-00 | B12: ABALOS, HILARIO O | C12: 100 | D12: 125 | E12: 66.7 | F12: 18 | G12: 45773 | H12: W | I12: NORTH | J12: INTRA 2025 | M12: =VLOOKUP(A12,#REF!,5,FALSE) -> #REF!
A13: 2870-00 | B13: ABALOS, HILARIO O | C13: 81 | D13: 125 | E13: 66.7 | F13: 18 | G13: 45619 | H13: W | I13: NORTH | J13: INTRA 2024 | M13: =VLOOKUP(A13,#REF!,5,FALSE) -> #REF!
A14: 2870-00 | B14: ABALOS, HILARIO O | C14: 99 | D14: 126 | E14: 70.6 | F14: 18 | G14: 45707 | H14: W | I14: SOUTH | J14: DCT 2025 | M14: =VLOOKUP(A14,#REF!,5,FALSE) -> #REF!
A15: 2870-00 | B15: ABALOS, HILARIO O | C15: 99 | D15: 126 | E15: 70.6 | F15: 18 | G15: 45375 | H15: W | I15: SOUTH | J15: DCT 2024 | M15: =VLOOKUP(A15,#REF!,5,FALSE) -> #REF!
A16: 2870-00 | B16: ABALOS, HILARIO O | C16: 91 | D16: 126 | E16: 70.6 | F16: 18 | G16: 45372 | H16: W | I16: SOUTH | J16: DCT 2024 | M16: =VLOOKUP(A16,#REF!,5,FALSE) -> #REF!
A17: 2870-00 | B17: ABALOS, HILARIO O | C17: 95 | D17: 126 | E17: 70.6 | F17: 18 | G17: 45570 | H17: W | I17: SOUTH | J17: CLUB CHAMP Q1 2025 | M17: =VLOOKUP(A17,#REF!,5,FALSE) -> #REF!
A18: 2870-00 | B18: ABALOS, HILARIO O | C18: 94 | D18: 126 | E18: 70.6 | F18: 18 | G18: 45577 | H18: W | I18: SOUTH | J18: CLUB CHAMP Q1 2025 | M18: =VLOOKUP(A18,#REF!,5,FALSE) -> #REF!
A19: 2870-00 | B19: ABALOS, HILARIO O | C19: 91 | D19: 126 | E19: 70.6 | F19: 18 | G19: 45297 | H19: W | I19: SOUTH | J19: CLUB CHAMP Q1 2024 | M19: =VLOOKUP(A19,#REF!,5,FALSE) -> #REF!
... A37: 7851-00 | B37: ADRIANO, JOSE ROBERTO | C37: 85 | D37: 126 | E37: 70.6 | F37: 18 | G37: 45304 | H37: W | I37: SOUTH | J37: CLUB CHAMP Q1 2024 | M37: =VLOOKUP(A37,#REF!,5,FALSE) -> #REF!
A38: 7851-00 | B38: ADRIANO, JOSE ROBERTO | C38: 43 | D38: 128 | E38: 33.8 | F38: F9 | G38: 45808 | H38: W | I38: NORTH | J38: BARKADAHAN 2025 | M38: =VLOOKUP(A38,#REF!,5,FALSE) -> #REF!
A39: 7851-00 | B39: ADRIANO, JOSE ROBERTO | C39: 89 | D39: 126 | E39: 70.6 | F39: 18 | G39: 45899 | H39: W | I39: SOUTH | J39: All Seniors 2025 | M39: =VLOOKUP(A39,#REF!,5,FALSE) -> #REF!
A40: 7073-00 | B40: AFRICA, ALEKHINE C. | C40: 94 | D40: 132 | E40: 68.8 | F40: 18 | G40: 45707 | H40: B | I40: NORTH | J40: DCT 2025 | M40: =VLOOKUP(A40,#REF!,5,FALSE) -> #REF!
A41: 7073-00 | B41: AFRICA, ALEKHINE C. | C41: 100 | D41: 134 | E41: 72.8 | F41: 18 | G41: 45710 | H41: B | I41: SOUTH | J41: DCT 2025 | M41: =VLOOKUP(A41,#REF!,5,FALSE) -> #REF!
A42: 8511-00 | B42: AGUAS, MARIE SIMONETTE | C42: 117 | D42: 129 | E42: 73.3 | F42: 18 | G42: 45914 | H42: R | I42: SOUTH | J42: PRESCUP 2025 | M42: =VLOOKUP(A42,#REF!,5,FALSE) -> #REF!
A43: 8135-00 | B43: AGUILA, ROMULO JR. | C43: 94 | D43: 125 | E43: 66.7 | F43: 18 | G43: 45619 | H43: W | I43: NORTH | J43: INTRA 2024 | M43: =VLOOKUP(A43,#REF!,5,FALSE) -> #REF!
A44: 2767-00 | B44: AGUILAR, ADOLFO JR B. | C44: 89 | D44: 134 | E44: 72.8 | F44: 18 | G44: 45550 | H44: B | I44: SOUTH | J44: PRESCUP 2024 | M44: =VLOOKUP(A44,#REF!,5,FALSE) -> #REF!
A45: 2767-00 | B45: AGUILAR, ADOLFO JR B. | C45: 92 | D45: 134 | E45: 72.8 | F45: 18 | G45: 45577 | H45: B | I45: SOUTH | J45: CLUB CHAMP Q1 2025 | M45: =VLOOKUP(A45,#REF!,5,FALSE) -> #REF!
A46: 2767-00 | B46: AGUILAR, ADOLFO JR B. | C46: 91 | D46: 134 | E46: 72.8 | F46: 18 | G46: 45297 | H46: B | I46: SOUTH | J46: CLUB CHAMP Q1 2024 | M46: =VLOOKUP(A46,#REF!,5,FALSE) -> #REF!
A47: 2767-00 | B47: AGUILAR, ADOLFO JR. | C47: 91 | D47: 134 | E47: 72.8 | F47: 18 | G47: 45914 | H47: B | I47: SOUTH | J47: PRESCUP 2025 | M47: =VLOOKUP(A47,#REF!,5,FALSE) -> #REF!
A48: 8528-00 | B48: AGUILAR, ANDRE PAOLO A. | C48: 85 | D48: 134 | E48: 72.8 | F48: 18 | G48: 45577 | H48: B | I48: SOUTH | J48: CLUB CHAMP Q1 2025 | M48: =VLOOKUP(A48,#REF!,5,FALSE) -> #REF!
A49: 8528-00 | B49: AGUILAR, ANDRE PAOLO A. | C49: 91 | D49: 134 | E49: 72.8 | F49: 18 | G49: 45570 | H49: B | I49: SOUTH | J49: CLUB CHAMP Q1 2025 | M49: =VLOOKUP(A49,#REF!,5,FALSE) -> #REF!
A50: 3309-00 | B50: AGUILAR, FRANCIS | C50: 109 | D50: 134 | E50: 72.8 | F50: 18 | G50: 45914 | H50: B | I50: SOUTH | J50: PRESCUP 2025 | M50: =VLOOKUP(A50,#REF!,5,FALSE) -> #REF!
... A67: 7776-00 | B67: ALBA, JASON J | C67: 102 | D67: 134 | E67: 72.8 | F67: 18 | G67: 45304 | H67: B | I67: SOUTH | J67: CLUB CHAMP Q1 2024 | M67: =VLOOKUP(A67,#REF!,5,FALSE) -> #REF!
A68: 3551-00 | B68: ALCANTARA, MARCELINO III CRISOSTOMO | C68: 50 | D68: 136 | E68: 36.6 | F68: F9 | G68: 45837 | H68: B | I68: SOUTH | J68: BARKADAHAN 2025 | M68: =VLOOKUP(A68,#REF!,5,FALSE) -> #REF!
A69: 3374-00 | B69: ALCANTARA, MARCELINO "MENCY" | C69: 89 | D69: 125 | E69: 66.7 | F69: 18 | G69: 45899 | H69: W | I69: NORTH | J69: All Seniors 2025 | M69: =VLOOKUP(A69,#REF!,5,FALSE) -> #REF!
A70: 3374-00 | B70: ALCANTARA, MARCELINO "MENCY" | C70: 0 | D70: 125 | E70: 66.7 | F70: 18 | G70: 45914 | H70: W | I70: NORTH | J70: PRESCUP 2025 | M70: =VLOOKUP(A70,#REF!,5,FALSE) -> #REF!
A71: 3551-00 | B71: ALCANTARA, MARCELINO III CRISOSTOMO | C71: 90 | D71: 134 | E71: 72.8 | F71: 18 | G71: 45774 | H71: B | I71: SOUTH | J71: INTRA 2025 | M71: =VLOOKUP(A71,#REF!,5,FALSE) -> #REF!
A72: 3551-00 | B72: ALCANTARA, MARCELINO III CRISOSTOMO | C72: 104 | D72: 132 | E72: 68.8 | F72: 18 | G72: 45773 | H72: B | I72: NORTH | J72: INTRA 2025 | M72: =VLOOKUP(A72,#REF!,5,FALSE) -> #REF!
A73: 7915-00 | B73: ALCANTARA, RODOLFO | C73: 102 | D73: 125 | E73: 66.7 | F73: 18 | G73: 45619 | H73: W | I73: NORTH | J73: INTRA 2024 | M73: =VLOOKUP(A73,#REF!,5,FALSE) -> #REF!
A74: 7915-00 | B74: ALCANTARA, RODOLFO | C74: 98 | D74: 134 | E74: 72.8 | F74: 18 | G74: 45710 | H74: B | I74: SOUTH | J74: DCT 2025 | M74: =VLOOKUP(A74,#REF!,5,FALSE) -> #REF!
A75: 7915-00 | B75: ALCANTARA, RODOLFO | C75: 87 | D75: 126 | E75: 70.6 | F75: 18 | G75: 45707 | H75: W | I75: SOUTH | J75: DCT 2025 | M75: =VLOOKUP(A75,#REF!,5,FALSE) -> #REF!
A76: 7915-00 | B76: ALCANTARA, RODOLFO | C76: 89 | D76: 135 | E76: 72 | F76: 18 | G76: 45375 | H76: B | I76: SOUTH | J76: DCT 2024 | M76: =VLOOKUP(A76,#REF!,5,FALSE) -> #REF!
A77: 7915-00 | B77: ALCANTARA, RODOLFO | C77: 105 | D77: 126 | E77: 70.6 | F77: 18 | G77: 45372 | H77: W | I77: SOUTH | J77: DCT 2024 | M77: =VLOOKUP(A77,#REF!,5,FALSE) -> #REF!
A78: 7643-00 | B78: ALDE, JOSE VICENTE | C78: 87 | D78: 126 | E78: 70.6 | F78: 18 | G78: 45899 | H78: W | I78: SOUTH | J78: All Seniors 2025 | M78: =VLOOKUP(A78,#REF!,5,FALSE) -> #REF!
A79: 7643-00 | B79: ALDE, JOSE VICENTE L. | C79: 82 | D79: 125 | E79: 66.7 | F79: 18 | G79: 45550 | H79: W | I79: NORTH | J79: PRESCUP 2024 | M79: =VLOOKUP(A79,#REF!,5,FALSE) -> #REF!
A80: 7643-00 | B80: ALDE, JOSE VICENTE L. | C80: 91 | D80: 125 | E80: 66.7 | F80: 18 | G80: 45773 | H80: W | I80: NORTH | J80: INTRA 2025 | M80: =VLOOKUP(A80,#REF!,5,FALSE) -> #REF!
... A82: 7643-00 | B82: ALDE, JOSE VICENTE L. | C82: 81 | D82: 125 | E82: 66.7 | F82: 18 | G82: 45619 | H82: W | I82: NORTH | J82: INTRA 2024 | M82: =VLOOKUP(A82,#REF!,5,FALSE) -> #REF!
A83: 7643-00 | B83: ALDE, JOSE VICENTE L. | C83: 39 | D83: 128 | E83: 33.8 | F83: F9 | G83: 45837 | H83: W | I83: NORTH | J83: BARKADAHAN 2025 | M83: =VLOOKUP(A83,#REF!,5,FALSE) -> #REF!
A84: 3403-00 | B84: ALEJANDRO, JEROU JOSE | C84: 103 | D84: 134 | E84: 72.8 | F84: 18 | G84: 45550 | H84: B | I84: SOUTH | J84: PRESCUP 2024 | M84: =VLOOKUP(A84,#REF!,5,FALSE) -> #REF!
A85: 3403-00 | B85: ALEJANDRO, JEROU JOSE | C85: 94 | D85: 132 | E85: 68.8 | F85: 18 | G85: 45773 | H85: B | I85: NORTH | J85: INTRA 2025 | M85: =VLOOKUP(A85,#REF!,5,FALSE) -> #REF!
A86: 3403-00 | B86: ALEJANDRO, JEROU JOSE | C86: 104 | D86: 134 | E86: 72.8 | F86: 18 | G86: 45774 | H86: B | I86: SOUTH | J86: INTRA 2025 | M86: =VLOOKUP(A86,#REF!,5,FALSE) -> #REF!
A87: 3403-00 | B87: ALEJANDRO, JEROU JOSE | C87: 89 | D87: 132 | E87: 68.8 | F87: 18 | G87: 45707 | H87: B | I87: NORTH | J87: DCT 2025 | M87: =VLOOKUP(A87,#REF!,5,FALSE) -> #REF!
A88: 3403-00 | B88: ALEJANDRO, JEROU JOSE | C88: 92 | D88: 134 | E88: 72.8 | F88: 18 | G88: 45710 | H88: B | I88: SOUTH | J88: DCT 2025 | M88: =VLOOKUP(A88,#REF!,5,FALSE) -> #REF!
A89: 3403-00 | B89: ALEJANDRO, JEROU JOSE | C89: 89 | D89: 135 | E89: 72 | F89: 18 | G89: 45375 | H89: B | I89: SOUTH | J89: DCT 2024 | M89: =VLOOKUP(A89,#REF!,5,FALSE) -> #REF!
A90: 3403-00 | B90: ALEJANDRO, JEROU JOSE | C90: 94 | D90: 135 | E90: 72 | F90: 18 | G90: 45372 | H90: B | I90: SOUTH | J90: DCT 2024 | M90: =VLOOKUP(A90,#REF!,5,FALSE) -> #REF!
A91: 3403-00 | B91: ALEJANDRO, JEROU JOSE | C91: 45 | D91: 138 | E91: 34.9 | F91: F9 | G91: 45830 | H91: B | I91: NORTH | J91: BARKADAHAN 2025 | M91: =VLOOKUP(A91,#REF!,5,FALSE) -> #REF!
A92: 7943-00 | B92: ALIÑO, CARLO | C92: 83 | D92: 134 | E92: 72.8 | F92: 18 | G92: 45914 | H92: B | I92: SOUTH | J92: PRESCUP 2025 | M92: =VLOOKUP(A92,#REF!,5,FALSE) -> #REF!
A93: 7943-00 | B93: ALINO, CARLO EDUARDO | C93: 95 | D93: 132 | E93: 68.8 | F93: 18 | G93: 45773 | H93: B | I93: NORTH | J93: INTRA 2025 | M93: =VLOOKUP(A93,#REF!,5,FALSE) -> #REF!
A94: 7943-00 | B94: ALINO, CARLO EDUARDO | C94: 89 | D94: 134 | E94: 72.8 | F94: 18 | G94: 45774 | H94: B | I94: SOUTH | J94: INTRA 2025 | M94: =VLOOKUP(A94,#REF!,5,FALSE) -> #REF!
A95: 7943-00 | B95: ALINO, CARLO EDUARDO | C95: 80 | D95: 134 | E95: 72.8 | F95: 18 | G95: 45710 | H95: B | I95: SOUTH | J95: DCT 2025 | M95: =VLOOKUP(A95,#REF!,5,FALSE) -> #REF!
A96: 7943-00 | B96: ALINO, CARLO EDUARDO | C96: 92 | D96: 132 | E96: 68.8 | F96: 18 | G96: 45707 | H96: B | I96: NORTH | J96: DCT 2025 | M96: =VLOOKUP(A96,#REF!,5,FALSE) -> #REF!
A97: 7943-00 | B97: ALINO, CARLO EDUARDO | C97: 83 | D97: 135 | E97: 72 | F97: 18 | G97: 45375 | H97: B | I97: SOUTH | J97: DCT 2024 | M97: =VLOOKUP(A97,#REF!,5,FALSE) -> #REF!
A98: 7943-00 | B98: ALINO, CARLO EDUARDO | C98: 80 | D98: 135 | E98: 72 | F98: 18 | G98: 45372 | H98: B | I98: SOUTH | J98: DCT 2024 | M98: =VLOOKUP(A98,#REF!,5,FALSE) -> #REF!
A99: 7943-00 | B99: ALINO, CARLO EDUARDO | C99: 86 | D99: 134 | E99: 72.8 | F99: 18 | G99: 45570 | H99: B | I99: SOUTH | J99: CLUB CHAMP Q1 2025 | M99: =VLOOKUP(A99,#REF!,5,FALSE) -> #REF!
A100: 7943-00 | B100: ALINO, CARLO EDUARDO | C100: 83 | D100: 134 | E100: 72.8 | F100: 18 | G100: 45577 | H100: B | I100: SOUTH | J100: CLUB CHAMP Q1 2025 | M100: =VLOOKUP(A100,#REF!,5,FALSE) -> #REF!
A101: 7943-00 | B101: ALINO, CARLO EDUARDO | C101: 93 | D101: 134 | E101: 72.8 | F101: 18 | G101: 45304 | H101: B | I101: SOUTH | J101: CLUB CHAMP Q1 2024 | M101: =VLOOKUP(A101,#REF!,5,FALSE) -> #REF!
A102: 7943-00 | B102: ALINO, CARLO EDUARDO | C102: 95 | D102: 134 | E102: 72.8 | F102: 18 | G102: 45297 | H102: B | I102: SOUTH | J102: CLUB CHAMP Q1 2024 | M102: =VLOOKUP(A102,#REF!,5,FALSE) -> #REF!
A103: 7943-00 | B103: ALINO, CARLO EDUARDO | C103: 46 | D103: 138 | E103: 34.9 | F103: F9 | G103: 45830 | H103: B | I103: NORTH | J103: BARKADAHAN 2025 | M103: =VLOOKUP(A103,#REF!,5,FALSE) -> #REF!
A104: 3585-03 | B104: ALMAZAN, BASILIO ISAAC | C104: 110 | D104: 134 | E104: 72.8 | F104: 18 | G104: 45914 | H104: B | I104: SOUTH | J104: PRESCUP 2025 | M104: =VLOOKUP(A104,#REF!,5,FALSE) -> #REF!
A105: 3585-00 | B105: ALMAZAN, BASILIO JR. | C105: 89 | D105: 125 | E105: 66.7 | F105: 18 | G105: 45914 | H105: W | I105: NORTH | J105: PRESCUP 2025 | M105: =VLOOKUP(A105,#REF!,5,FALSE) -> #REF!
A106: 3585-02 | B106: ALMAZAN, EARL EDUARD | C106: 102 | D106: 134 | E106: 72.8 | F106: 18 | G106: 45914 | H106: B | I106: SOUTH | J106: PRESCUP 2025 | M106: =VLOOKUP(A106,#REF!,5,FALSE) -> #REF!
A107: 7471-00 | B107: ALMEDA, RENE | C107: 117 | D107: 125 | E107: 66.7 | F107: 18 | G107: 45914 | H107: W | I107: NORTH | J107: PRESCUP 2025 | M107: =VLOOKUP(A107,#REF!,5,FALSE) -> #REF!
A108: 7471-00 | B108: ALMEDA, RENE | C108: 98 | D108: 125 | E108: 66.7 | F108: 18 | G108: 45899 | H108: W | I108: NORTH | J108: All Seniors 2025 | M108: =VLOOKUP(A108,#REF!,5,FALSE) -> #REF!
A109: 7471-00 | B109: ALMEDA, RENE T. | C109: 91 | D109: 126 | E109: 70.6 | F109: 18 | G109: 45707 | H109: W | I109: SOUTH | J109: DCT 2025 | M109: =VLOOKUP(A109,#REF!,5,FALSE) -> #REF!
A110: 7471-00 | B110: ALMEDA, RENE T. | C110: 97 | D110: 126 | E110: 70.6 | F110: 18 | G110: 45710 | H110: W | I110: SOUTH | J110: DCT 2025 | M110: =VLOOKUP(A110,#REF!,5,FALSE) -> #REF!
A111: 8332-00 | B111: AMBATALI, ANDREW PAOLO | C111: 89 | D111: 134 | E111: 72.8 | F111: 18 | G111: 45550 | H111: B | I111: SOUTH | J111: PRESCUP 2024 | M111: =VLOOKUP(A111,#REF!,5,FALSE) -> #REF!
A112: 8332-00 | B112: AMBATALI, ANDREW PAOLO | C112: 90 | D112: 134 | E112: 72.8 | F112: 18 | G112: 45619 | H112: B | I112: SOUTH | J112: INTRA 2024 | M112: =VLOOKUP(A112,#REF!,5,FALSE) -> #REF!
A113: 8374-00 | B113: AMPARO, AMORE | C113: 100 | D113: 129 | E113: 73.3 | F113: 18 | G113: 45914 | H113: R | I113: SOUTH | J113: PRESCUP 2025 | M113: =VLOOKUP(A113,#REF!,5,FALSE) -> #REF!
A114: 3039-00 | B114: AN, YOUNG JAE | C114: 93 | D114: 126 | E114: 70.6 | F114: 18 | G114: 45577 | H114: W | I114: SOUTH | J114: CLUB CHAMP Q1 2025 | M114: =VLOOKUP(A114,#REF!,5,FALSE) -> #REF!
A115: 8282-00 | B115: ANDOYO, LEONEL | C115: 90 | D115: 134 | E115: 72.8 | F115: 18 | G115: 45550 | H115: B | I115: SOUTH | J115: PRESCUP 2024 | M115: =VLOOKUP(A115,#REF!,5,FALSE) -> #REF!
... A118: 8282-00 | B118: ANDOYO, LEONEL | C118: 96 | D118: 134 | E118: 72.8 | F118: 18 | G118: 45577 | H118: B | I118: SOUTH | J118: CLUB CHAMP Q1 2025 | M118: =VLOOKUP(A118,#REF!,5,FALSE) -> #REF!
A119: 8282-00 | B119: ANDOYO, LEONEL | C119: 42 | D119: 138 | E119: 34.9 | F119: F9 | G119: 45822 | H119: B | I119: NORTH | J119: BARKADAHAN 2025 | M119: =VLOOKUP(A119,#REF!,5,FALSE) -> #REF!
A120: 8282-00 | B120: ANDOYO, LEONEL | C120: 46 | D120: 138 | E120: 34.9 | F120: F9 | G120: 45809 | H120: B | I120: NORTH | J120: BARKADAHAN 2025 | M120: =VLOOKUP(A120,#REF!,5,FALSE) -> #REF!
A121: 8282-00 | B121: ANDOYO, LEONEL | C121: 93 | D121: 134 | E121: 72.8 | F121: 18 | G121: 45871 | H121: B | I121: SOUTH | J121: BARKADAHAN 2025 | M121: =VLOOKUP(A121,#REF!,5,FALSE) -> #REF!
A122: 3459-03 | B122: ANG, ANDREW | C122: 99 | D122: 134 | E122: 72.8 | F122: 18 | G122: 45914 | H122: B | I122: SOUTH | J122: PRESCUP 2025 | M122: =VLOOKUP(A122,#REF!,5,FALSE) -> #REF!
A123: 3459-00 | B123: ANG, MALVIN | C123: 117 | D123: 134 | E123: 72.8 | F123: 18 | G123: 45914 | H123: B | I123: SOUTH | J123: PRESCUP 2025 | M123: =VLOOKUP(A123,#REF!,5,FALSE) -> #REF!
A124: 3459-00 | B124: ANG, MALVIN | C124: 116 | D124: 132 | E124: 68.8 | F124: 18 | G124: 45707 | H124: B | I124: NORTH | J124: DCT 2025 | M124: =VLOOKUP(A124,#REF!,5,FALSE) -> #REF!
A125: 3459-00 | B125: ANG, MALVIN | C125: 116 | D125: 134 | E125: 72.8 | F125: 18 | G125: 45710 | H125: B | I125: SOUTH | J125: DCT 2025 | M125: =VLOOKUP(A125,#REF!,5,FALSE) -> #REF!
A126: 3459-00 | B126: ANG, MALVIN | C126: 123 | D126: 135 | E126: 72 | F126: 18 | G126: 45372 | H126: B | I126: SOUTH | J126: DCT 2024 | M126: =VLOOKUP(A126,#REF!,5,FALSE) -> #REF!
A127: 3459-00 | B127: ANG, MALVIN | C127: 121 | D127: 135 | E127: 72 | F127: 18 | G127: 45375 | H127: B | I127: SOUTH | J127: DCT 2024 | M127: =VLOOKUP(A127,#REF!,5,FALSE) -> #REF!
A128: 3081-00 | B128: ANG, RANDY | C128: 44 | D128: 136 | E128: 36.6 | F128: F9 | G128: 45851 | H128: B | I128: SOUTH | J128: BARKADAHAN 2025 | M128: =VLOOKUP(A128,#REF!,5,FALSE) -> #REF!
A129: 7344-00 | B129: ANGELES, LEVIE G. | C129: 85 | D129: 125 | E129: 66.7 | F129: 18 | G129: 45550 | H129: W | I129: NORTH | J129: PRESCUP 2024 | M129: =VLOOKUP(A129,#REF!,5,FALSE) -> #REF!
A130: 7344-00 | B130: ANGELES, LEVIE G. | C130: 91 | D130: 125 | E130: 66.7 | F130: 18 | G130: 45619 | H130: W | I130: NORTH | J130: INTRA 2024 | M130: =VLOOKUP(A130,#REF!,5,FALSE) -> #REF!
A131: 7344-00 | B131: ANGELES, LEVIE G. | C131: 92 | D131: 126 | E131: 70.6 | F131: 18 | G131: 45372 | H131: W | I131: SOUTH | J131: DCT 2024 | M131: =VLOOKUP(A131,#REF!,5,FALSE) -> #REF!
A132: 7344-00 | B132: ANGELES, LEVIE G. | C132: 89 | D132: 126 | E132: 70.6 | F132: 18 | G132: 45375 | H132: W | I132: SOUTH | J132: DCT 2024 | M132: =VLOOKUP(A132,#REF!,5,FALSE) -> #REF!
A133: 7344-00 | B133: ANGELES, LEVIE G. | C133: 85 | D133: 126 | E133: 70.6 | F133: 18 | G133: 45577 | H133: W | I133: SOUTH | J133: CLUB CHAMP Q1 2025 | M133: =VLOOKUP(A133,#REF!,5,FALSE) -> #REF!
A134: 7344-00 | B134: ANGELES, LEVIE G. | C134: 94 | D134: 126 | E134: 70.6 | F134: 18 | G134: 45570 | H134: W | I134: SOUTH | J134: CLUB CHAMP Q1 2025 | M134: =VLOOKUP(A134,#REF!,5,FALSE) -> #REF!
A135: 7344-00 | B135: ANGELES, LEVIE G. | C135: 44 | D135: 128 | E135: 33.8 | F135: F9 | G135: 45822 | H135: W | I135: NORTH | J135: BARKADAHAN 2025 | M135: =VLOOKUP(A135,#REF!,5,FALSE) -> #REF!
A136: 7344-00 | B136: ANGELES, LEVIE G. | C136: 44 | D136: 128 | E136: 33.8 | F136: F9 | G136: 45808 | H136: W | I136: NORTH | J136: BARKADAHAN 2025 | M136: =VLOOKUP(A136,#REF!,5,FALSE) -> #REF!
...

Sheet Sheet3

Sheet Sheet4
A1: account_no | B1: Name | C1: course_id | D1: tee_id | E1: whs_no
A2: 8511-00 | B2: AGUAS, MARIE SIMONETTE | E2: 1001820 | F2: WACK
A3: 2767-00 | B3: AGUILAR, ADOLFO JR B. | E3: 34680
A4: 3551-00 | B4: ALCANTARA, MARCELINO III CRISOSTOMO | E4: 10704
A5: 7943-00 | B5: ALINO, CARLO EDUARDO | E5: 41643
A6: 3585-03 | B6: ALMAZAN, BASILIO ISAAC | E6: 71919 | F6: FH
A7: 3585-00 | B7: ALMAZAN, BASILIO JR. | E7: 29274 | F7: FH
A8: 3585-02 | B8: ALMAZAN, EARL EDUARD | E8: 71918
A9: 7471-00 | B9: ALMEDA, RENE T. | E9: 6090
A10: 3039-00 | B10: AN, YOUNG JAE | E10: 77412
A11: 3081-00 | B11: ANG, RANDY | E11: -
A12: 2146-00 | B12: ANONAS , GERARDO B. | E12: 8651
A13: 8199-00 | B13: AQUINO, ALEX | E13: -
A14: 8008-00 | B14: ATAYDE, THERESA REMEDIOS "RIZZA" T | E14: 49360
A15: 8264-00 | B15: ATENCIO, JANUARIO JESUS | E15: 70912
A16: 2480-00 | B16: AVILA, ROMEO M. | E16: 12563
A17: 3002-00 | B17: BARCELON, JOSE ANCHETA | E17: 68282
A18: 8289-00 | B18: BARRETTO, DON RYAN | E18: 73145
A19: 3577-00 | B19: BAYHON, VINCENT PATRICK | E19: 72313
A20: 2614-00 | B20: BENITEZ, TOMAS JULIO A. | E20: 8750
A21: 8398-00 | B21: BERNAS, JORGE ALEXANDER | E21: 21647
A22: 8569-00 | B22: BONGAT, JEFFERSON | E22: 1000963
A23: 8218-00 | B23: BONGAT, NOEL | E23: 12607
A24: 3350-00 | B24: BULUT, ELIAS JR. | E24: 78245
A25: 3004-00 | B25: CABANELA, RICH- O | E25: 36080
... A27: 8449-00 | B27: CAGALINGAN, JOSE PAOLO | E27: 65740
A28: 8309-00 | B28: CALDERON, CHRIS ALLEN | E28: #N/A
A29: 8145-00 | B29: CAPARROS, IRENE MARGOT | E29: 26936
A30: 1058-00 | B30: CAPARROS, MARVIN A. | E30: 412
A31: 1058-01 | B31: CAPARROS, MILDRED MYRA | E31: 26938
A32: 187-01 | B32: CARLOS, ARSENIA | E32: 8815
A33: 187-00 | B33: CARLOS, ARTHUR | E33: 8816
A34: 7676-03 | B34: CARPESO, ZHAQUILL ELDON | E34: 17924
A35: 686-00 | B35: CARPIO, CARLO | E35: 8825
A36: 686-01 | B36: CARPIO, SYLVIA | E36: 8826
A37: 3482-00 | B37: CERENO, CONRAD | E37: 67681
A38: 3541-02 | B38: CHAM, ETHAN ALEXANDER | E38: 10004377
A39: 8203-03 | B39: CHAN, AERIN | E39: 78119
A40: 8203-01 | B40: CHAN, JEFFREI | E40: 73954
... A42: 8059-00 | B42: CHENG, ANTHONY | E42: 26964
A43: 3626-00 | B43: CHUA, SAM RICHMOND | E43: #N/A
A44: 3624-001 | B44: CHUA, VANESSA | E44: 1002349
A45: 8500-00 | B45: CHUNG, GIAN TIMOTHY | E45: 72796
A46: 8079-00 | B46: CLAVIO, ARNOLD | E46: 50770
A47: 3511-04 | B47: CO, ARIANA | E47: #N/A
A48: 3511-02 | B48: CO, BRYCE WILLIAM SY | E48: 77584
A49: 3080-00 | B49: CO, JEFFREY ANG | E49: 41405
A50: 3511-03 | B50: CO, RAPHAEL DAVID | E50: #N/A
A51: 3511-01 | B51: CO, STEPHANIE | E51: #N/A
A52: 3511-00 | B52: CO, WINSTON | E52: #N/A
A53: 2860-00 | B53: CONDE, PHILIP | E53: 15839
A54: 3243-03 | B54: CRUZ, AIDEN | E54: 80791
A55: 8197-00 | B55: CRUZ, ANNIKA LOUISE | E55: 72876
A56: 3514-03 | B56: CRUZ, JUAN ANTONIO | E56: 77076
A57: 8407-02 | B57: CURRAN, EMILIO | E57: 44516
A58: 2753-00 | B58: DANDAN, ALEXANDER | E58: 10444
A59: 3021-00 | B59: DARJUAN, ANTONIO JR. | E59: 44123
A60: 8028-02 | B60: DARJUAN, SEBASTIAN MIGUEL | E60: 78117
A61: 8450-01 | B61: DATOC, RJ | E61: 41750
A62: 3127-00 | B62: DE JESUS, DANIEL | E62: 43632
A63: 7227-00 | B63: DE OCAMPO, ROBERTO F. | E63: 27048
A64: 3127-00 | B64: DE VERA, EFREN | E64: 49426
... A68: 3284-00 | B68: DOMINGO, RENNY E | E68: 50410
A69: 3029-02 | B69: DONATO, CHELSEY | E69: #N/A
A70: 3575-00 | B70: DY SUN, ALLEN | E70: #N/A
A71: 8310-01 | B71: DY SUN, LAURIE | E71: #N/A
A72: 3557-02 | B72: DY, VIVIENNE KYRIE | E72: #N/A
A73: 275-00 | B73: ESGUERRA, MA. CECILIA NG | E73: #N/A
A74: 3159-00 | B74: FEDEREZO, ROGER M | E74: #N/A
A75: 0624-00 | B75: FERNANDO, MARCELO JR. | E75: #N/A
A76: 2789-00 | B76: FIGURA, FRANCISCO B. | E76: #N/A
A77: 3395-01 | B77: FLORES, RICARDO JR. | E77: #N/A
A78: 3276-01 | B78: FREGIL, JERE | E78: #N/A
A79: 8123-01 | B79: GALANG, VIC | E79: #N/A
A80: 7608-00 | B80: GARROTE, ANDY | E80: #N/A
... A142: 3362-01 | B142: MARTIREZ, PAOLO | E142: #N/A
A143: 8432-00 | B143: MEJIA, MANUEL FLORENCIO IV | E143: #N/A | F143: M
A144: 8571-01 | B144: MENDOZA, JESUS ANGELO | E144: #N/A
A145: 7894-01 | B145: MOLATO, ART | E145: #N/A
A146: 8576-00 | B146: MONTANIER, FREDERICK | E146: #N/A
A147: 3150-02 | B147: MORALES, EMILIO LORENZO S | E147: #N/A
A148: 2880-01 | B148: MORALES, LUIS HERMES "LOUIE" | E148: #N/A
A149: 7963-01 | B149: NAM, YEONSOOK | E149: #N/A
A150: 3528-00 | B150: NARVACAN, RODERICK GIL | E150: #N/A
A151: 8367-00 | B151: NGUI, RICHARD ANTHONY | E151: #N/A
A152: 2841-00 | B152: NOVELA, MARLON | E152: #N/A
A153: 7978-00 | B153: OCAMPO, CHRISTOPHER PATRICK GREY | E153: #N/A
A154: 684-00 | B154: OLIVES, JOSE ANTONIO | E154: #N/A
A155: 7863-00 | B155: OLIVES, MARCO ANTONIO | E155: #N/A
... A251: 2530-05 | B251: ZHANG, JASON | E251: #N/A

Sheet Sheet1 (2)
A1: account_no | B1: last_name | C1: first_name | D1: middle_name | E1: whs_no | F1: BIRTHDAY | G1: sex | H1: NAME | J1: account_no | K1: last_name | L1: first_name | M1: middle_name | N1: whs_no | O1: BIRTHDAY | P1: sex | Q1: EMAIL | R1: NAME
A2: 0015-00 | B2: PUYAT | C2: RAYMUND | E2: 9724 | F2: 23378 | G2: M | H2: PUYAT, RAYMUND | J2: 0015-00 | K2: PUYAT | L2: RAYMUND | N2: 9724 | O2: 23378 | P2: M | Q2: rbpuyat@gmail.com | R2: PUYAT, RAYMUND
A3: 0017-00 | B3: CRUZ | C3: JOSE "PINGGOY" | E3: 8933 | F3: 14278 | G3: M | H3: CRUZ, JOSE "PINGGOY" | J3: 0017-00 | K3: CRUZ | L3: JOSE "PINGGOY" | N3: 8933 | O3: 14278 | P3: M | Q3: hebhighendbroadcast@gmail.com | R3: CRUZ, JOSE "PINGGOY"
A4: 0021-00 | B4: MESINA | C4: JACINTO "JESS" | E4: 9539 | F4: 13804 | G4: M | H4: MESINA, JACINTO "JESS" | J4: 0021-00 | K4: MESINA | L4: JACINTO "JESS" | N4: 9539 | O4: 13804 | P4: M | Q4: jessmesina16@gmail.com | R4: MESINA, JACINTO "JESS"
A5: 0033-00 | B5: GO | C5: EDGARDO "EDDIE" | E5: 9178 | F5: 20824 | G5: M | H5: GO, EDGARDO "EDDIE" | J5: 0033-00 | K5: GO | L5: EDGARDO "EDDIE" | N5: 9178 | O5: 20824 | P5: M | Q5: gts_center@yahoo.com | R5: GO, EDGARDO "EDDIE"
A6: 0034-00 | B6: LOPEZ | C6: INOCENCIO "ENNIE" | E6: 9451 | F6: 18448 | G6: M | H6: LOPEZ, INOCENCIO "ENNIE" | J6: 0034-00 | K6: LOPEZ | L6: INOCENCIO "ENNIE" | N6: 9451 | O6: 18448 | P6: M | Q6: lopezinocencio692@gmail.com | R6: LOPEZ, INOCENCIO "ENNIE"
A7: 0053-00 | B7: CAPISTRANO | C7: EDMUNDO "JUN" | E7: 8809 | F7: 18375 | G7: M | H7: CAPISTRANO, EDMUNDO "JUN" | J7: 0053-00 | K7: CAPISTRANO | L7: EDMUNDO "JUN" | N7: 8809 | O7: 18375 | P7: M | Q7: capistrano911@yahoo.com | R7: CAPISTRANO, EDMUNDO "JUN"
A8: 0058-00 | B8: ALVENDIA | C8: ROLANDO | E8: 8640 | F8: 19520 | G8: M | H8: ALVENDIA, ROLANDO | J8: 0058-00 | K8: ALVENDIA | L8: ROLANDO | N8: 8640 | O8: 19520 | P8: M | Q8: rmalvendia2005@yahoo.com | R8: ALVENDIA, ROLANDO
A9: 0076-00 | B9: LAZO | C9: SAMSON "SAMMY" | E9: 9359 | F9: 16279 | G9: M | H9: LAZO, SAMSON "SAMMY" | J9: 0076-00 | K9: LAZO | L9: SAMSON "SAMMY" | N9: 9359 | O9: 16279 | P9: M | Q9: sammylazo@yahoo.com | R9: LAZO, SAMSON "SAMMY"
A10: 0081-00 | B10: LITTAUA | C10: DIONISIO "DIONNY" | E10: 9433 | F10: 22664 | G10: M | H10: LITTAUA, DIONISIO "DIONNY" | J10: 0081-00 | K10: LITTAUA | L10: DIONISIO "DIONNY" | N10: 9433 | O10: 22664 | P10: M | Q10: littcon@gmail.com | R10: LITTAUA, DIONISIO "DIONNY"
A11: 0081-01 | B11: LITTAUA | C11: MA TERESA | E11: 9434 | F11: 24231 | G11: F | H11: LITTAUA, MA TERESA | J11: 0081-01 | K11: LITTAUA | L11: MA TERESA | N11: 9434 | O11: 24231 | P11: F | R11: LITTAUA, MA TERESA
A12: 0094-00 | B12: STROEM | C12: LEA ANA | E12: 9958 | F12: 21976 | G12: F | H12: STROEM, LEA ANA | J12: 0094-00 | K12: STROEM | L12: LEA ANA | N12: 9958 | O12: 21976 | P12: F | Q12: leastroem@yahoo.com | R12: STROEM, LEA ANA
A13: 0094-01 | B13: STROEM | C13: RUNE | E13: 75420 | F13: 22695 | G13: M | H13: STROEM, RUNE | J13: 0094-01 | K13: STROEM | L13: RUNE | N13: 75420 | O13: 22695 | P13: M | Q13: stroemrune@gmail.com | R13: STROEM, RUNE
A14: 0109-00 | B14: SO | C14: WILSON | E14: 75039 | F14: 18840 | G14: M | H14: SO, WILSON | J14: 0109-00 | K14: SO | L14: WILSON | N14: 75039 | O14: 18840 | P14: M | Q14: wilson@toneguide.com.ph | R14: SO, WILSON
A15: 0121-00 | B15: PEGELS | C15: VIOLETA "VIOLY" | E15: 9693 | F15: 20881 | G15: F | H15: PEGELS, VIOLETA "VIOLY" | J15: 0121-00 | K15: PEGELS | L15: VIOLETA "VIOLY" | N15: 9693 | O15: 20881 | P15: F | Q15: violypegels@rocketmail.com | R15: PEGELS, VIOLETA "VIOLY"
A16: 0122-00 | B16: ONG | C16: JOSELITO "JOJO" | E16: 9613 | F16: 19884 | G16: M | H16: ONG, JOSELITO "JOJO" | J16: 0122-00 | K16: ONG | L16: JOSELITO "JOJO" | N16: 9613 | O16: 19884 | P16: M | Q16: joselitodong@gmail.com | R16: ONG, JOSELITO "JOJO"
A17: 0123-00 | B17: GO | C17: MARCELINO "DAUDO" | E17: 9184 | F17: 18359 | G17: M | H17: GO, MARCELINO "DAUDO" | J17: 0123-00 | K17: GO | L17: MARCELINO "DAUDO" | N17: 9184 | O17: 18359 | P17: M | Q17: daudogo@gmail.com | R17: GO, MARCELINO "DAUDO"
A18: 0131-00 | B18: UY | C18: SAMUEL | E18: 10072 | F18: 22890 | G18: M | H18: UY, SAMUEL | J18: 0131-00 | K18: UY | L18: SAMUEL | N18: 10072 | O18: 22890 | P18: M | Q18: jenny_uy63@yahoo.com | R18: UY, SAMUEL
A19: 0137-00 | B19: SAN AGUSTIN | C19: ARISTEO "ARIS" | E19: 9843 | F19: 17874 | G19: M | H19: SAN AGUSTIN, ARISTEO "ARIS" | J19: 0137-00 | K19: SAN AGUSTIN | L19: ARISTEO "ARIS" | N19: 9843 | O19: 17874 | P19: M | Q19: asa747@hotmail.com | R19: SAN AGUSTIN, ARISTEO "ARIS"
A20: 0139-00 | B20: ABAYA | C20: RODOLFO | E20: 8593 | F20: 22943 | G20: M | H20: ABAYA, RODOLFO | J20: 0139-00 | K20: ABAYA | L20: RODOLFO | N20: 8593 | O20: 22943 | P20: M | Q20: roddyabaya@mac.com | R20: ABAYA, RODOLFO
A21: 0144-00 | B21: REVERENTE JR | C21: BENITO | E21: 9771 | F21: 11698 | G21: M | H21: REVERENTE JR, BENITO | J21: 0144-00 | K21: REVERENTE JR | L21: BENITO | N21: 9771 | O21: 11698 | P21: M | R21: REVERENTE JR, BENITO
A22: 0164-00 | B22: VILCHEZ JR | C22: JOSE "BONG" | E22: 20796 | F22: 19196 | G22: M | H22: VILCHEZ JR, JOSE "BONG" | J22: 0164-00 | K22: VILCHEZ JR | L22: JOSE "BONG" | N22: 20796 | O22: 19196 | P22: M | Q22: jrvilchez27@gmail.com | R22: VILCHEZ JR, JOSE "BONG"
A23: 0172-00 | B23: VELAYO JR | C23: JACINTO | E23: 10084 | F23: 23304 | G23: M | H23: VELAYO JR, JACINTO | J23: 0172-00 | K23: VELAYO JR | L23: JACINTO | N23: 10084 | O23: 23304 | P23: M | Q23: jun.velayo54@gmail.com | R23: VELAYO JR, JACINTO
A24: 0174-00 | B24: CASA | C24: ORLANDO "ORLY" | E24: 15719 | F24: 24902 | G24: M | H24: CASA, ORLANDO "ORLY" | J24: 0174-00 | K24: CASA | L24: ORLANDO "ORLY" | N24: 15719 | O24: 24902 | P24: M | Q24: orlsc@yahoo.com | R24: CASA, ORLANDO "ORLY"
A25: 0187-00 | B25: CARLOS | C25: ARTHUR "ART" | E25: 8816 | F25: 19723 | G25: M | H25: CARLOS, ARTHUR "ART" | J25: 0187-00 | K25: CARLOS | L25: ARTHUR "ART" | N25: 8816 | O25: 19723 | P25: M | Q25: art_constech@yahoo.com | R25: CARLOS, ARTHUR "ART"
A26: 0187-01 | B26: CARLOS | C26: ARSENIA "ZENY" | E26: 8815 | F26: 20369 | G26: F | H26: CARLOS, ARSENIA "ZENY" | J26: 0187-01 | K26: CARLOS | L26: ARSENIA "ZENY" | N26: 8815 | O26: 20369 | P26: F | Q26: zehn_constech@yahoo.com.ph | R26: CARLOS, ARSENIA "ZENY"
A27: 0207-00 | B27: BAUTISTA | C27: ALFREDO "FREDDIE" | E27: 8739 | F27: 21868 | G27: M | H27: BAUTISTA, ALFREDO "FREDDIE" | J27: 0207-00 | K27: BAUTISTA | L27: ALFREDO "FREDDIE" | N27: 8739 | O27: 21868 | P27: M | Q27: alfjbautista@gmail.com | R27: BAUTISTA, ALFREDO "FREDDIE"
A28: 0215-00 | B28: VIDANES | C28: D. PAULO | E28: 10094 | F28: 23188 | G28: M | H28: VIDANES, D. PAULO | J28: 0215-00 | K28: VIDANES | L28: D. PAULO | N28: 10094 | O28: 23188 | P28: M | Q28: paulvidanes@gmail.com | R28: VIDANES, D. PAULO
A29: 0220-00 | B29: DE LEON JR | C29: INOCENCIO | E29: 8970 | F29: 14298 | G29: M | H29: DE LEON JR, INOCENCIO | J29: 0220-00 | K29: DE LEON JR | L29: INOCENCIO | N29: 8970 | O29: 14298 | P29: M | Q29: de_leon1939@yahoo.com | R29: DE LEON JR, INOCENCIO
A30: 0225-00 | B30: DELA CRUZ | C30: BENITO "BENNY" | E30: 8991 | F30: 17011 | G30: M | H30: DELA CRUZ, BENITO "BENNY" | J30: 0225-00 | K30: DELA CRUZ | L30: BENITO "BENNY" | N30: 8991 | O30: 17011 | P30: M | Q30: bentcz@yahoo.com | R30: DELA CRUZ, BENITO "BENNY"
A31: 0242-00 | B31: VILLALUNA JR. | C31: JOSE | E31: 10103 | F31: 14658 | G31: M | H31: VILLALUNA JR., JOSE | J31: 0242-00 | K31: VILLALUNA JR. | L31: JOSE | N31: 10103 | O31: 14658 | P31: M | Q31: jecvpxm@yahoo.com.ph | R31: VILLALUNA JR., JOSE
A32: 0262-00 | B32: MENDOZA | C32: HONOR S. | E32: 9531 | F32: 22914 | G32: M | H32: MENDOZA, HONOR S. | J32: 0262-00 | K32: MENDOZA | L32: HONOR S. | N32: 9531 | O32: 22914 | P32: M | Q32: hsm7775@yahoo.com | R32: MENDOZA, HONOR S.
A33: 0275-00 | B33: ESGUERRA | C33: CECILE | E33: 9065 | F33: 22669 | G33: F | H33: ESGUERRA, CECILE | J33: 0275-00 | K33: ESGUERRA | L33: CECILE | N33: 9065 | O33: 22669 | P33: F | Q33: cjnesguerra@yahoo.com | R33: ESGUERRA, CECILE
... A39: 0306-00 | B39: TANCHI JR | C39: ERNESTO | E39: 10011 | F39: 17320 | G39: M | H39: TANCHI JR, ERNESTO | J39: 0306-00 | K39: TANCHI JR | L39: ERNESTO | N39: 10011 | O39: 17320 | P39: M | Q39: ernietanchi@yahoo.com | R39: TANCHI JR, ERNESTO
A40: 0307-00 | B40: SUMULONG | C40: LORENZO | E40: 70138 | F40: 2075 | G40: M | H40: SUMULONG, LORENZO | J40: 0307-00 | K40: SUMULONG | L40: LORENZO | N40: 70138 | O40: 2075 | P40: M | R40: SUMULONG, LORENZO
A41: 0333-00 | B41: HUANG | C41: PING | E41: 76905 | F41: 15600 | G41: M | H41: HUANG, PING | J41: 0333-00 | K41: HUANG | L41: PING | N41: 76905 | O41: 15600 | P41: M | R41: HUANG, PING
A42: 0358-00 | B42: TUASON | C42: ELIZABETH | E42: 76445 | F42: 13518 | G42: F | H42: TUASON, ELIZABETH | J42: 0358-00 | K42: TUASON | L42: ELIZABETH | N42: 76445 | O42: 13518 | P42: F | R42: TUASON, ELIZABETH
A43: 0362-00 | B43: UNLAY | C43: RAYMOND PETER "PETE" | E43: 22311 | F43: 25180 | G43: M | H43: UNLAY, RAYMOND PETER "PETE" | J43: 0362-00 | K43: UNLAY | L43: RAYMOND PETER "PETE" | N43: 22311 | O43: 25180 | P43: M | Q43: peter.unlay@yahoo.com | R43: UNLAY, RAYMOND PETER "PETE"
A44: 0368-00 | B44: DE UBAGO | C44: ANTONIO | E44: 21767 | F44: 17852 | G44: M | H44: DE UBAGO, ANTONIO | J44: 0368-00 | K44: DE UBAGO | L44: ANTONIO | N44: 21767 | O44: 17852 | P44: M | Q44: tonydeu131@gmail.com | R44: DE UBAGO, ANTONIO
A45: 0380-00 | B45: CORONEL | C45: JOEL NAPOLEON | E45: 8910 | F45: 21438 | G45: M | H45: CORONEL, JOEL NAPOLEON | J45: 0380-00 | K45: CORONEL | L45: JOEL NAPOLEON | N45: 8910 | O45: 21438 | P45: M | Q45: arthur_coronel@yahoo.com | R45: CORONEL, JOEL NAPOLEON
A46: 0395-00 | B46: ZAPANTA | C46: JAIME "JIMMY" | E46: 10175 | F46: 14445 | G46: M | H46: ZAPANTA, JAIME "JIMMY" | J46: 0395-00 | K46: ZAPANTA | L46: JAIME "JIMMY" | N46: 10175 | O46: 14445 | P46: M | Q46: jimmyzapanta1@yahoo.com | R46: ZAPANTA, JAIME "JIMMY"
A47: 0406-00 | B47: ZAMORA | C47: TEODORICO | E47: 10171 | F47: 14062 | G47: M | H47: ZAMORA, TEODORICO | J47: 0406-00 | K47: ZAMORA | L47: TEODORICO | N47: 10171 | O47: 14062 | P47: M | Q47: catherinemabato@yahoo.com | R47: ZAMORA, TEODORICO
A48: 0412-00 | B48: RAMOSO | C48: JOSEPH "JOEY" | E48: 9749 | F48: 24906 | G48: M | H48: RAMOSO, JOSEPH "JOEY" | J48: 0412-00 | K48: RAMOSO | L48: JOSEPH "JOEY" | N48: 9749 | O48: 24906 | P48: M | Q48: atr@mozcom.com | R48: RAMOSO, JOSEPH "JOEY"
A49: 0421-00 | B49: DE GUZMAN | C49: MARCELINO "MAR" | E49: 8964 | F49: 17649 | G49: M | H49: DE GUZMAN, MARCELINO "MAR" | J49: 0421-00 | K49: DE GUZMAN | L49: MARCELINO "MAR" | N49: 8964 | O49: 17649 | P49: M | Q49: mardegu426@gmail.com | R49: DE GUZMAN, MARCELINO "MAR"
A50: 0438-00 | B50: GREGORIO | C50: VICENTE | E50: 9207 | F50: 12694 | G50: M | H50: GREGORIO, VICENTE | J50: 0438-00 | K50: GREGORIO | L50: VICENTE | N50: 9207 | O50: 12694 | P50: M | Q50: pggl.law@gmail.com | R50: GREGORIO, VICENTE
A51: 0453-00 | B51: CHUA | C51: MICHAEL | E51: 8875 | F51: 24631 | G51: M | H51: CHUA, MICHAEL | J51: 0453-00 | K51: CHUA | L51: MICHAEL | N51: 8875 | O51: 24631 | P51: M | Q51: angietiuchua@yahoo.com | R51: CHUA, MICHAEL
A52: 0459-00 | B52: DEL ROSARIO JR | C52: MAXIMO | E52: 8982 | F52: 15280 | G52: M | H52: DEL ROSARIO JR, MAXIMO | J52: 0459-00 | K52: DEL ROSARIO JR | L52: MAXIMO | N52: 8982 | O52: 15280 | P52: M | Q52: maxbethdelrosario@gmail.com | R52: DEL ROSARIO JR, MAXIMO
A53: 0460-00 | B53: LABRADOR | C53: LEO PERFECTO | E53: 9336 | F53: 23122 | G53: M | H53: LABRADOR, LEO PERFECTO | J53: 0460-00 | K53: LABRADOR | L53: LEO PERFECTO | N53: 9336 | O53: 23122 | P53: M | Q53: cfc_leo@ymail.com | R53: LABRADOR, LEO PERFECTO
A54: 0468-00 | B54: GUERRERO | C54: GERARDO "GERRY" | E54: 9217 | F54: 19262 | G54: M | H54: GUERRERO, GERARDO "GERRY" | J54: 0468-00 | K54: GUERRERO | L54: GERARDO "GERRY" | N54: 9217 | O54: 19262 | P54: M | Q54: gjguerrero1952@yahoo.com | R54: GUERRERO, GERARDO "GERRY"
... A61: 0503-00 | B61: CORNEJO | C61: ADRIAN JEAN CLAUDE "AJ" | E61: 32498 | F61: 21175 | G61: M | H61: CORNEJO, ADRIAN JEAN CLAUDE "AJ" | J61: 0503-00 | K61: CORNEJO | L61: ADRIAN JEAN CLAUDE "AJ" | N61: 32498 | O61: 21175 | P61: M | Q61: tom.consolacion1221@gmail.com | R61: CORNEJO, ADRIAN JEAN CLAUDE "AJ"
A62: 0510-00 | B62: LANUZA JR | C62: CAESAR "JUN" | E62: 21137 | F62: 16984 | G62: M | H62: LANUZA JR, CAESAR "JUN" | J62: 0510-00 | K62: LANUZA JR | L62: CAESAR "JUN" | N62: 21137 | O62: 16984 | P62: M | R62: LANUZA JR, CAESAR "JUN"
A63: 0515-00 | B63: ALARILLA | C63: ARTURO "ART" | E63: 8617 | F63: 16969 | G63: M | H63: ALARILLA, ARTURO "ART" | J63: 0515-00 | K63: ALARILLA | L63: ARTURO "ART" | N63: 8617 | O63: 16969 | P63: M | Q63: arthur369a@gmail.com | R63: ALARILLA, ARTURO "ART"
A64: 0526-00 | B64: TANJUATCO | C64: JOSE | E64: 10020 | F64: 18716 | G64: M | H64: TANJUATCO, JOSE | J64: 0526-00 | K64: TANJUATCO | L64: JOSE | N64: 10020 | O64: 18716 | P64: M | Q64: litotanjuatco@yahoo.com | R64: TANJUATCO, JOSE
A65: 0527-00 | B65: TANSENGCO | C65: RAYMOND | E65: 10021 | F65: 20628 | G65: M | H65: TANSENGCO, RAYMOND | J65: 0527-00 | K65: TANSENGCO | L65: RAYMOND | N65: 10021 | O65: 20628 | P65: M | Q65: rtansengco@gmail.com | R65: TANSENGCO, RAYMOND
A66: 0530-00 | B66: CONSOLACION | C66: THOMAS "TOM" | E66: 8905 | F66: 18751 | G66: M | H66: CONSOLACION, THOMAS "TOM" | J66: 0530-00 | K66: CONSOLACION | L66: THOMAS "TOM" | N66: 8905 | O66: 18751 | P66: M | R66: CONSOLACION, THOMAS "TOM"
A67: 0533-00 | B67: PERLAS | C67: FORTUNATO | E67: 10508 | F67: 14167 | G67: M | H67: PERLAS, FORTUNATO | J67: 0533-00 | K67: PERLAS | L67: FORTUNATO | N67: 10508 | O67: 14167 | P67: M | Q67: fqperlas@teltrends.com.ph | R67: PERLAS, FORTUNATO
A68: 0535-00 | B68: SANTIAGO III | C68: SEBASTIAN "CHITO" | E68: 9866 | F68: 19273 | G68: M | H68: SANTIAGO III, SEBASTIAN "CHITO" | J68: 0535-00 | K68: SANTIAGO III | L68: SEBASTIAN "CHITO" | N68: 9866 | O68: 19273 | P68: M | Q68: sebastianvsantiago@gmail.com | R68: SANTIAGO III, SEBASTIAN "CHITO"
A69: 0537-00 | B69: ESTRADA | C69: RAYMUNDO "YEYET" | E69: 9076 | F69: 23168 | G69: M | H69: ESTRADA, RAYMUNDO "YEYET" | J69: 0537-00 | K69: ESTRADA | L69: RAYMUNDO "YEYET" | N69: 9076 | O69: 23168 | P69: M | Q69: rexst_ph@yahoo.com | R69: ESTRADA, RAYMUNDO "YEYET"
A70: 0543-00 | B70: FUGOSO | C70: RODOLFO "ARVIE /RV" VALERIANO | E70: 9132 | F70: 27933 | G70: M | H70: FUGOSO, RODOLFO "ARVIE /RV" VALERIANO | J70: 0543-00 | K70: FUGOSO | L70: RODOLFO "ARVIE /RV" VALERIANO | N70: 9132 | O70: 27933 | P70: M | Q70: arviefugoso@yahoo.com | R70: FUGOSO, RODOLFO "ARVIE /RV" VALERIANO
A71: 0543-01 | B71: FUGOSO | C71: VIRGINIA | E71: 1000761 | F71: 27214 | G71: F | H71: FUGOSO, VIRGINIA | J71: 0543-01 | K71: FUGOSO | L71: VIRGINIA | N71: 1000761 | O71: 27214 | P71: F | Q71: vipvipp2011@gmail.com | R71: FUGOSO, VIRGINIA
A72: 0543-02 | B72: FUGOSO | C72: ISABELLE | E72: 1000760 | F72: 39739 | G72: F | H72: FUGOSO, ISABELLE | J72: 0543-02 | K72: FUGOSO | L72: ISABELLE | N72: 1000760 | O72: 39739 | P72: F | Q72: isabellefugoso@gmail.com | R72: FUGOSO, ISABELLE
A73: 0548-00 | B73: ABEJO | C73: TEOFILO | E73: 8594 | F73: 22727 | G73: M | H73: ABEJO, TEOFILO | J73: 0548-00 | K73: ABEJO | L73: TEOFILO | N73: 8594 | O73: 22727 | P73: M | Q73: timabejo@gmail.com | R73: ABEJO, TEOFILO
A74: 0553-00 | B74: HUANG | C74: JOHN | E74: 9256 | F74: 20983 | G74: M | H74: HUANG, JOHN | J74: 0553-00 | K74: HUANG | L74: JOHN | N74: 9256 | O74: 20983 | P74: M | Q74: jhuang@yahoo.com | R74: HUANG, JOHN
A75: 0566-00 | B75: UNSON | C75: ANTONIO | E75: 10062 | F75: 20471 | G75: M | H75: UNSON, ANTONIO | J75: 0566-00 | K75: UNSON | L75: ANTONIO | N75: 10062 | O75: 20471 | P75: M | Q75: noniunson@yahoo.com | R75: UNSON, ANTONIO
A76: 0571-00 | B76: PASILIAO | C76: LUCAS "LUKE" | E76: 9687 | F76: 16728 | G76: M | H76: PASILIAO, LUCAS "LUKE" | J76: 0571-00 | K76: PASILIAO | L76: LUCAS "LUKE" | N76: 9687 | O76: 16728 | P76: M | Q76: lucaspasiliao@yahoo.com | R76: PASILIAO, LUCAS "LUKE"
A77: 0579-00 | B77: ESTANISLAO | C77: RAFAEL "PENG" | E77: 9075 | F77: 18561 | G77: M | H77: ESTANISLAO, RAFAEL "PENG" | J77: 0579-00 | K77: ESTANISLAO | L77: RAFAEL "PENG" | N77: 9075 | O77: 18561 | P77: M | Q77: rpe1025@gmail.com | R77: ESTANISLAO, RAFAEL "PENG"
A78: 0584-00 | B78: LIAMZON | C78: ROBERTO ANTONIO "BOBBY" | E78: 9393 | F78: 24237 | G78: M | H78: LIAMZON, ROBERTO ANTONIO "BOBBY" | J78: 0584-00 | K78: LIAMZON | L78: ROBERTO ANTONIO "BOBBY" | N78: 9393 | O78: 24237 | P78: M | Q78: bobbyliamzon@yahoo.com | R78: LIAMZON, ROBERTO ANTONIO "BOBBY"
... A85: 0646-00 | B85: LIAMZON JR | C85: ROMEO THADDEUS | E85: 9391 | F85: 23410 | G85: M | H85: LIAMZON JR, ROMEO THADDEUS | J85: 0646-00 | K85: LIAMZON JR | L85: ROMEO THADDEUS | N85: 9391 | O85: 23410 | P85: M | Q85: litatabelisma@gmail.com | R85: LIAMZON JR, ROMEO THADDEUS
A86: 0665-01 | B86: NARCELLES | C86: MYRNA | E86: 9568 | F86: 16971 | G86: F | H86: NARCELLES, MYRNA | J86: 0665-01 | K86: NARCELLES | L86: MYRNA | N86: 9568 | O86: 16971 | P86: F | R86: NARCELLES, MYRNA
A87: 0672-00 | B87: VILLA | C87: ZALDY | E87: 1000013 | F87: 20889 | G87: M | H87: VILLA, ZALDY | J87: 0672-00 | K87: VILLA | L87: ZALDY | N87: 1000013 | O87: 20889 | P87: M | Q87: rey_engineering@yahoo.com | R87: VILLA, ZALDY
A88: 0672-06 | B88: VILLA | C88: ZJ TRISTAN | E88: 1005912 | F88: 39617 | G88: M | H88: VILLA, ZJ TRISTAN | J88: 0672-06 | K88: VILLA | L88: ZJ TRISTAN | N88: 1005912 | O88: 39617 | P88: M | Q88: zjvilla1824@gmail.com | R88: VILLA, ZJ TRISTAN
A89: 0684-00 | B89: OLIVES | C89: JOSE ANTONIO | E89: 31225 | F89: 18539 | G89: M | H89: OLIVES, JOSE ANTONIO | J89: 0684-00 | K89: OLIVES | L89: JOSE ANTONIO | N89: 31225 | O89: 18539 | P89: M | Q89: tonyolives61@gmail.com | R89: OLIVES, JOSE ANTONIO
A90: 0686-00 | B90: CARPIO | C90: CARLO | E90: 8825 | F90: 24841 | G90: M | H90: CARPIO, CARLO | J90: 0686-00 | K90: CARPIO | L90: CARLO | N90: 8825 | O90: 24841 | P90: M | Q90: cjcarpio@texicongroup.com | R90: CARPIO, CARLO
A91: 0686-01 | B91: CARPIO | C91: SYLVIA "JET" | E91: 8826 | F91: 22211 | G91: F | H91: CARPIO, SYLVIA "JET" | J91: 0686-01 | K91: CARPIO | L91: SYLVIA "JET" | N91: 8826 | O91: 22211 | P91: F | Q91: jette_carpio@yahoo.com | R91: CARPIO, SYLVIA "JET"
A92: 0686-02 | B92: CARPIO | C92: EMILIO JOSE | E92: 10711 | F92: 38411 | G92: M | H92: CARPIO, EMILIO JOSE | J92: 0686-02 | K92: CARPIO | L92: EMILIO JOSE | N92: 10711 | O92: 38411 | P92: M | Q92: ejccarpio92@gmail.com | R92: CARPIO, EMILIO JOSE
A93: 0700-00 | B93: SOLIS | C93: RONALD "POPE" | E93: 9946 | F93: 22111 | G93: M | H93: SOLIS, RONALD "POPE" | J93: 0700-00 | K93: SOLIS | L93: RONALD "POPE" | N93: 9946 | O93: 22111 | P93: M | Q93: solispope@yahoo.com | R93: SOLIS, RONALD "POPE"
A94: 0718-00 | B94: SAMANIEGO | C94: ALBERT "ABET" | E94: 10607 | F94: 25501 | G94: M | H94: SAMANIEGO, ALBERT "ABET" | J94: 0718-00 | K94: SAMANIEGO | L94: ALBERT "ABET" | N94: 10607 | O94: 25501 | P94: M | Q94: albertsamaniego68@yahoo.com | R94: SAMANIEGO, ALBERT "ABET"
A95: 0788-00 | B95: AYESA | C95: MARCELO | E95: 8702 | F95: 17732 | G95: M | H95: AYESA, MARCELO | J95: 0788-00 | K95: AYESA | L95: MARCELO | N95: 8702 | O95: 17732 | P95: M | Q95: mfayesa@gmail.com | R95: AYESA, MARCELO
A96: 0799-00 | B96: TAYAG | C96: MANOLITO "LITO" | E96: 10026 | F96: 22811 | G96: M | H96: TAYAG, MANOLITO "LITO" | J96: 0799-00 | K96: TAYAG | L96: MANOLITO "LITO" | N96: 10026 | O96: 22811 | P96: M | Q96: manolitotayag@noemail.com | R96: TAYAG, MANOLITO "LITO"
A97: 0802-00 | B97: GUTIERREZ | C97: RICARDO "KADO" | E97: 9223 | F97: 17283 | G97: M | H97: GUTIERREZ, RICARDO "KADO" | J97: 0802-00 | K97: GUTIERREZ | L97: RICARDO "KADO" | N97: 9223 | O97: 17283 | P97: M | Q97: kadogutierrez@gmail.com | R97: GUTIERREZ, RICARDO "KADO"
A98: 0849-00 | B98: CHEOK | C98: EDWARD | E98: 8857 | F98: 21367 | G98: M | H98: CHEOK, EDWARD | J98: 0849-00 | K98: CHEOK | L98: EDWARD | N98: 8857 | O98: 21367 | P98: M | Q98: edcheok@yahoo.com | R98: CHEOK, EDWARD
... A105: 0927-00 | B105: FLORES II | C105: JAIME MA | E105: 10725 | F105: 23312 | G105: M | H105: FLORES II, JAIME MA | J105: 0927-00 | K105: FLORES II | L105: JAIME MA | N105: 10725 | O105: 23312 | P105: M | Q105: jimboflores@gmail.com | R105: FLORES II, JAIME MA
A106: 0929-01 | B106: CABANGBANG | C106: CLARITA | E106: 10335 | F106: 22244 | G106: F | H106: CABANGBANG, CLARITA | J106: 0929-01 | K106: CABANGBANG | L106: CLARITA | N106: 10335 | O106: 22244 | P106: F | R106: CABANGBANG, CLARITA
A107: 0932-00 | B107: SUDARIO | C107: JOSE FERLU | E107: 9962 | F107: 17111 | G107: M | H107: SUDARIO, JOSE FERLU | J107: 0932-00 | K107: SUDARIO | L107: JOSE FERLU | N107: 9962 | O107: 17111 | P107: M | Q107: joseferlusudario@gmail.com | R107: SUDARIO, JOSE FERLU
A108: 0934-00 | B108: ABALOS | C108: JONATHAN CLEMENT "JON" | E108: 10670 | F108: 25152 | G108: M | H108: ABALOS, JONATHAN CLEMENT "JON" | J108: 0934-00 | K108: ABALOS | L108: JONATHAN CLEMENT "JON" | N108: 10670 | O108: 25152 | P108: M | Q108: jonabalos2000@gmail.com | R108: ABALOS, JONATHAN CLEMENT "JON"
A109: 0940-00 | B109: GUATNO | C109: GUMERCINDO | E109: 9210 | F109: 19737 | G109: M | H109: GUATNO, GUMERCINDO | J109: 0940-00 | K109: GUATNO | L109: GUMERCINDO | N109: 9210 | O109: 19737 | P109: M | Q109: gmguatno22@gmail.com | R109: GUATNO, GUMERCINDO
A110: 0986-00 | B110: SAMANIEGO | C110: RODOLFO "RUDY" | E110: 9836 | F110: 14755 | G110: M | H110: SAMANIEGO, RODOLFO "RUDY" | J110: 0986-00 | K110: SAMANIEGO | L110: RODOLFO "RUDY" | N110: 9836 | O110: 14755 | P110: M | Q110: samaniegorodolfo24@gmail.com | R110: SAMANIEGO, RODOLFO "RUDY"
A111: 1001-00 | B111: DAVID | C111: RAMON "MON" | E111: 8954 | F111: 21512 | G111: M | H111: DAVID, RAMON "MON" | J111: 1001-00 | K111: DAVID | L111: RAMON "MON" | N111: 8954 | O111: 21512 | P111: M | Q111: ramonsdavid@yahoo.com | R111: DAVID, RAMON "MON"
A112: 1016-00 | B112: SAN JUAN | C112: JOSE ERWIN | E112: 25840 | F112: 24772 | G112: M | H112: SAN JUAN, JOSE ERWIN | J112: 1016-00 | K112: SAN JUAN | L112: JOSE ERWIN | N112: 25840 | O112: 24772 | P112: M | Q112: joeysanjuan1027@icloud.com | R112: SAN JUAN, JOSE ERWIN
A113: 1027-00 | B113: ARBATIN | C113: JOSE "JOE" | E113: 8667 | F113: 16199 | G113: M | H113: ARBATIN, JOSE "JOE" | J113: 1027-00 | K113: ARBATIN | L113: JOSE "JOE" | N113: 8667 | O113: 16199 | P113: M | Q113: joearbatin@yahoo.com | R113: ARBATIN, JOSE "JOE"
A114: 1058-00 | B114: CAPARROS | C114: MARVIN A. | E114: 412 | F114: 25305 | G114: M | H114: CAPARROS, MARVIN A. | J114: 1058-00 | K114: CAPARROS | L114: MARVIN A. | N114: 412 | O114: 25305 | P114: M | Q114: macaparros@pldtdsl.net | R114: CAPARROS, MARVIN A.
A115: 1058-01 | B115: CAPARROS | C115: MILDRED MYRA | E115: 26938 | F115: 25440 | G115: F | H115: CAPARROS, MILDRED MYRA | J115: 1058-01 | K115: CAPARROS | L115: MILDRED MYRA | N115: 26938 | O115: 25440 | P115: F | Q115: myracaparros@yahoo.com | R115: CAPARROS, MILDRED MYRA
A116: 1072-00 | B116: BAUZA | C116: NESTOR | E116: 8741 | F116: 19104 | G116: M | H116: BAUZA, NESTOR | J116: 1072-00 | K116: BAUZA | L116: NESTOR | N116: 8741 | O116: 19104 | P116: M | Q116: nabauza.corrotech@gmail.com | R116: BAUZA, NESTOR
A117: 1073-00 | B117: JORGE | C117: RAOUL | E117: 27216 | F117: 22903 | G117: M | H117: JORGE, RAOUL | J117: 1073-00 | K117: JORGE | L117: RAOUL | N117: 27216 | O117: 22903 | P117: M | Q117: raoul.jorge@gmail.com | R117: JORGE, RAOUL
A118: 1079-00 | B118: LADANGA | C118: FLORENCIO "FLOR" | E118: 9342 | F118: 17476 | G118: M | H118: LADANGA, FLORENCIO "FLOR" | J118: 1079-00 | K118: LADANGA | L118: FLORENCIO "FLOR" | N118: 9342 | O118: 17476 | P118: M | Q118: florencioladanga@gmail.com | R118: LADANGA, FLORENCIO "FLOR"
... A129: 1234-00 | B129: CASTAÑEDA IV | C129: JOSE REMIGIO "JONG" | E129: 8828 | F129: 25281 | G129: M | H129: CASTAÑEDA IV, JOSE REMIGIO "JONG" | J129: 1234-00 | K129: CASTAÑEDA IV | L129: JOSE REMIGIO "JONG" | N129: 8828 | O129: 25281 | P129: M | Q129: jong.castaneda@nykgroup.com | R129: CASTAÑEDA IV, JOSE REMIGIO "JONG"
A130: 1234-02 | B130: CASTAÑEDA | C130: JOSE MIGUEL "MAIO" | E130: 10769 | F130: 37906 | G130: M | H130: CASTAÑEDA, JOSE MIGUEL "MAIO" | J130: 1234-02 | K130: CASTAÑEDA | L130: JOSE MIGUEL "MAIO" | N130: 10769 | O130: 37906 | P130: M | R130: CASTAÑEDA, JOSE MIGUEL "MAIO"
A131: 1256-00 | B131: JALANDONI | C131: MARIO | E131: 9270 | F131: 18522 | G131: M | H131: JALANDONI, MARIO | J131: 1256-00 | K131: JALANDONI | L131: MARIO | N131: 9270 | O131: 18522 | P131: M | Q131: mcvjalandoni@gmail.com | R131: JALANDONI, MARIO
A132: 1258-00 | B132: PANLASIGUI | C132: ROGERIO "OGENG" | E132: 9662 | F132: 20767 | G132: M | H132: PANLASIGUI, ROGERIO "OGENG" | J132: 1258-00 | K132: PANLASIGUI | L132: ROGERIO "OGENG" | N132: 9662 | O132: 20767 | P132: M | Q132: rbpanlasigui@yahoo.com | R132: PANLASIGUI, ROGERIO "OGENG"
A133: 1260-00 | B133: CHUA | C133: HOWARD | E133: 48450 | F133: 26019 | G133: M | H133: CHUA, HOWARD | J133: 1260-00 | K133: CHUA | L133: HOWARD | N133: 48450 | O133: 26019 | P133: M | Q133: hocmgc@yahoo.com.ph | R133: CHUA, HOWARD
...

Sheet Sheet1
A1: account_no | B1: last_name | C1: first_name | D1: middle_name | E1: whs_no | F1: BIRTHDAY | G1: sex | H1: EMAIL
A2: 0081-01 | B2: LITTAUA | C2: MA TERESA | E2: 9434 | F2: 24231 | G2: F
A3: 0144-00 | B3: REVERENTE JR | C3: BENITO | E3: 9771 | F3: 11698 | G3: M
A4: 0307-00 | B4: SUMULONG | C4: LORENZO | E4: 70138 | F4: 2075 | G4: M
A5: 0333-00 | B5: HUANG | C5: PING | E5: 76905 | F5: 15600 | G5: M
A6: 0358-00 | B6: TUASON | C6: ELIZABETH | E6: 76445 | F6: 13518 | G6: F
A7: 0510-00 | B7: LANUZA JR | C7: CAESAR "JUN" | E7: 21137 | F7: 16984 | G7: M
A8: 0530-00 | B8: CONSOLACION | C8: THOMAS "TOM" | E8: 8905 | F8: 18751 | G8: M
A9: 0665-01 | B9: NARCELLES | C9: MYRNA | E9: 9568 | F9: 16971 | G9: F
A10: 0929-01 | B10: CABANGBANG | C10: CLARITA | E10: 10335 | F10: 22244 | G10: F
A11: 1234-02 | B11: CASTAÑEDA | C11: JOSE MIGUEL "MAIO" | E11: 10769 | F11: 37906 | G11: M
A12: 1501-00 | B12: SILVA | C12: DINA | E12: 9932 | F12: 13619 | G12: F
A13: 2097-00 | B13: CU UNJIENG | C13: ROMAN | E13: 8940 | F13: 25477 | G13: M
... A17: 2367-00 | B17: ONGKIKO | C17: SONIA | E17: 9622 | F17: 12318 | G17: F
A18: 2530-06 | B18: ZHANG | C18: ABIGAIL | F18: 37974 | G18: F
A19: 2599-04 | B19: GREGORE | C19: ANGELICA NOUELLE | E19: 75651 | F19: 36924 | G19: F
A20: 2654-00 | B20: ROBLES | C20: DANILO | E20: 9799 | F20: 22480 | G20: M
A21: 2673-00 | B21: JARANTILLA JR | C21: FEDERICO | E21: 9275 | F21: 13676 | G21: M
A22: 2709-00 | B22: TAN | C22: EDWIN | E22: 10718 | F22: 20827 | G22: M
A23: 2718-00 | B23: ROLDAN | C23: JAMES | E23: 10303 | F23: 24479 | G23: M
A24: 2733-00 | B24: BAKUNAWA | C24: MANUEL "BUTCH" R. | E24: 10273 | F24: 31766 | G24: M
A25: 2776-00 | B25: APUHIN | C25: EVANGELINE "VANGIE" | E25: 8656 | F25: 23302 | G25: F
A26: 2824-00 | B26: KUBO | C26: ATSUSHI | E26: 44804 | F26: 26442 | G26: M
A27: 3076-03 | B27: BORROMEO | C27: MARIA MONICA | E27: 77565 | F27: 35189 | G27: F
A28: 3118-02 | B28: SEE | C28: DAMIEN MARCUS | E28: 49922 | F28: 38101 | G28: M
A29: 3219-02 | B29: ESCALADA | C29: EMMANUELLE | E29: 68879 | F29: 38407 | G29: F
A30: 3221-01 | B30: LAUREL | C30: JOSE ARSENIO | E30: 21142 | F30: 32483 | G30: M
... A36: 3511-03 | B36: CO | C36: RAPHAEL DAVID | E36: 1009246 | F36: 40386 | G36: M
A37: 3511-04 | B37: CO | C37: ARIANA | F37: 41878 | G37: F
A38: 3513-00 | B38: YANG | C38: HONG MING | E38: 77230 | F38: 28035 | G38: M
A39: 3514-03 | B39: CRUZ | C39: JUAN ANTONIO ''JUANTON'' P | E39: 77076 | F39: 41115 | G39: M
A40: 3574-00 | B40: SEE | C40: ROBIN | E40: 1002727 | F40: 37681 | G40: M
A41: 3637-04 | B41: CHUA | C41: JOHN | E41: 1008942 | F41: 41038 | G41: M
A42: 3696-02 | B42: GUICO | C42: MIGUEL KRISTOFF | E42: 1001291 | F42: 40092 | G42: M
A43: 7116-00 | B43: MENDOZA | C43: NESTOR "JAY" | E43: 41034 | F43: 41622 | G43: M
A44: 7493-02 | B44: PABLICO | C44: LUIGI BRIAN | E44: 14867 | F44: 33312 | G44: M
A45: 7508-01 | B45: LEGARDA | C45: JENNIFER | E45: 10201 | F45: 24582 | G45: F
A46: 7957-03 | B46: LEE | C46: CIAN STEPHEN | E46: 71466 | F46: 38299 | G46: M
A47: 8054-03 | B47: DE GUZMAN | C47: EMMANUEL "MANOLO" | E47: 75896 | F47: 38535 | G47: M
A48: 8062-00 | B48: UNTALAN | C48: MYLA | E48: 66488 | F48: 25799 | G48: F
A49: 8095-02 | B49: RODRIGUEZ | C49: MARYA ALEXANDRIA | E49: 1008066 | F49: 41098 | G49: F
... A58: 8511-01 | B58: SY | C58: STEVEN U. | E58: 27554 | F58: 24460 | G58: M
A59: 3575-02 | B59: DY SUN | C59: ADAM JOSE GAVINO B. | F59: 42572 | G59: M
A60: 8031-00 | B60: HERNANDEZ | C60: RICARDO "SONNY" | E60: 67953 | F60: 21622 | G60: M | H60: 07kenz14@gmail.com
A61: 0908-00 | B61: ALARILLA | C61: ROBERT | E61: 8619 | F61: 16918 | G61: M | H61: 0908-00@abc.com
A62: 8452-00 | B62: LACAP | C62: JOSEPH | E62: 1009081 | F62: 30914 | G62: M | H62: 1rjajauction@gmail.com
A63: 2688-02 | B63: ILLESCAS | C63: ERIC JOHN "EJ" | E63: 20892 | F63: 42143 | G63: M | H63: 268802@noemail.com
A64: 2696-04 | B64: CORPUS | C64: CARL JANO | E64: 38156 | F64: 37100 | G64: M | H64: 2696-04@abc.com
A65: 3590-04 | B65: TAN | C65: GEOFFREY | E65: 67874 | F65: 40185 | G65: M | H65: 359004@noemail.com
A66: 8028-03 | B66: DARJUAN | C66: SEBASTIAN MIGUEL | E66: 78117 | F66: 42955 | G66: M | H66: 802803@noemail.com
A67: 2976-00 | B67: PARK | C67: JUNG KI | E67: 1001757 | F67: 19140 | G67: M | H67: a01052120259@gmail.com
A68: 8253-00 | B68: MAGCALING | C68: JOUMER | E68: 73303 | F68: 28433 | G68: M | H68: aaac_10@yahoo.com
A69: 3554-01 | B69: ACUÑA | C69: JOSE MARI | E69: 1005078 | F69: 23048 | G69: M | H69: aagolfnut7@yahoo.com
A70: 7504-00 | B70: HERNANDEZ | C70: ALEXANDER LUIS | E70: 9241 | F70: 22885 | G70: M | H70: aah.sweetfusion@gmail.com
A71: 8153-00 | B71: TAN | C71: AARON DANIEL | E71: 79899 | F71: 34002 | G71: M | H71: aarontan0202@gmail.com
... A126: 8098-00 | B126: SAVELLANO | C126: ALEXANDRA DENISE S. | E126: 69448 | F126: 34880 | G126: F | H126: alexsavellano@gmail.com
A127: 8199-00 | B127: AQUINO | C127: ALEX | F127: 22776 | G127: M | H127: alexvaquino@hotmail.com
A128: 0207-00 | B128: BAUTISTA | C128: ALFREDO "FREDDIE" | E128: 8739 | F128: 21868 | G128: M | H128: alfjbautista@gmail.com
A129: 7534-00 | B129: BENGZON | C129: ALFONSO "ALI" | E129: 68236 | F129: 24320 | G129: M | H129: alfonsobengzon@yahoo.com
A130: 1407-00 | B130: LACAP | C130: ALFONSO | E130: 9337 | F130: 21080 | G130: M | H130: alfonsolacap@gmail.com
A131: 1380-00 | B131: CHUA | C131: ALFREDO | E131: 8870 | F131: 19397 | G131: M | H131: alfredochualu@yahoo.com
A132: 2711-01 | B132: LIN | C132: ANITA | E132: 75885 | F132: 21037 | G132: F | H132: alin8557@yahoo.com
A133: 2823-00 | B133: DY | C133: EDGAR ALLAN | E133: 10691 | F133: 27117 | G133: M | H133: allandy168@yahoo.com
A134: 8309-00 | B134: CALDERON | C134: CHRIS ALLEN | E134: 67246 | F134: 29031 | G134: M | H134: allen.golf@yahoo.com
A135: 3324-00 | B135: VALENCIA | C135: ALLEN | E135: 68752 | F135: 25400 | G135: M | H135: allenarizalavalencia@gmail.com
A136: 3575-00 | B136: DY SUN | C136: ALLEN | E136: 21035 | F136: 29284 | G136: M | H136: allendysun@yahoo.com
A137: 2793-00 | B137: SAYO | C137: ANTONIO "ANTON" | E137: 10567 | F137: 19210 | G137: M | H137: allsayo@yahoo.com
A138: 7471-00 | B138: ALMEDA | C138: RENE T. | E138: 6090 | F138: 21045 | G138: M | H138: almedarene@gmail.com
A139: 8264-00 | B139: ATENCIO | C139: JANUARIO JESUS | E139: 70912 | F139: 22648 | G139: M | H139: almer@januarius.ph
... A274: 7353-00 | B274: SAM | C274: BONIFACIO | E274: 9834 | F274: 20336 | G274: M | H274: bluesapphire904@icloud.com
A275: 3494-00 | B275: GONZALES | C275: BENEDICTO | F275: 21895 | G275: M | H275: bmg_lister@yahoo.com
A276: 7493-00 | B276: PABLICO | C276: BENITO "BENJO" | E276: 9637 | F276: 20535 | G276: M | H276: bmpablico@yahoo.com.ph
A277: 7066-00 | B277: ANGANGCO | C277: RAFAEL "BOBBIE" | E277: 8647 | F277: 21517 | G277: M | H277: bobangangco@yahoo.com
A278: 8180-00 | B278: FERRIOLS | C278: ROBERTO SEGUNDO "BOB" | E278: 6443 | F278: 26094 | G278: M | H278: bobby.ferriols@yahoo.com
A279: 1450-00 | B279: NARCISO | C279: ROBERTO | E279: 9570 | F279: 20882 | G279: M | H279: bobby.narciso@gmail.com
A280: 3119-00 | B280: GABRIEL | C280: ROBERTO "BOBBY" | E280: 12885 | F280: 26450 | G280: M | H280: bobbygabriel72@gmail.com
A281: 0584-00 | B281: LIAMZON | C281: ROBERTO ANTONIO "BOBBY" | E281: 9393 | F281: 24237 | G281: M | H281: bobbyliamzon@yahoo.com
A282: 2583-00 | B282: HENSON | C282: ROBERT "BOB" | E282: 9233 | F282: 23763 | G282: M | H282: bobhenson_hcc@yahoo.com
A283: 3040-00 | B283: SEGOVIA | C283: FERNANDO SIXTO "BOB" | E283: 72282 | F283: 22134 | G283: M | H283: bobsegovia48@yahoo.com
A284: 2741-00 | B284: SY | C284: JASON | E284: 10418 | F284: 26681 | G284: M | H284: boh.jason.sy@gmail.com
A285: 2783-00 | B285: LACHICA | C285: RALPH KENNETH | E285: 9338 | F285: 30381 | G285: M | H285: bokenlachica@gmail.com
A286: 8475-00 | B286: VILLAVICENCIO | C286: VICTOR | E286: 1005635 | F286: 30825 | G286: M | H286: bokie523@gmail.com
A287: 3309-01 | B287: AGUILAR | C287: RIBONNETTE | E287: 1000219 | F287: 29147 | G287: F | H287: bonaguilar@gmail.com
... A312: 3258-00 | B312: KOHCHET-CHUA | C312: CALVIN | E312: 14755 | F312: 25666 | G312: M | H312: calvinkc888@gmail.com
A313: 3045-04 | B313: YU | C313: CAMERYN | F313: 41955 | G313: F | H313: cameryn@yahoo.com
A314: 0053-00 | B314: CAPISTRANO | C314: EDMUNDO "JUN" | E314: 8809 | F314: 18375 | G314: M | H314: capistrano911@yahoo.com
A315: 3209-00 | B315: CAPULI | C315: RODERICK | E315: 65945 | F315: 24912 | G315: M | H315: capulierick@gmail.com
A316: 8454-00 | B316: REALUYO | C316: CARLITO | E316: 36628 | F316: 22895 | G316: M | H316: carlito.realuyo@yahoo.com
A317: 7943-00 | B317: ALINO | C317: CARLO EDUARDO | E317: 41643 | F317: 32494 | G317: M | H317: carlo.alino@ymail.com
A318: 8160-00 | B318: QUIMSON | C318: CARLO | E318: 10815 | F318: 35893 | G318: M | H318: carlo.quimson@peterpaul.com.ph
A319: 8117-00 | B319: SINGIAN | C319: CARLO | E319: 32011 | F319: 29037 | G319: M | H319: carlo.singian@gmail.com
A320: 3177-00 | B320: MENDOZA | C320: CARLO | E320: 67808 | F320: 22198 | G320: M | H320: carlo_a_mendoza@yahoo.com
A321: 3506-00 | B321: TAGAYUNA | C321: CARLO | E321: 77564 | F321: 30611 | G321: M | H321: carlo_tagayuna@live.com
A322: 3301-00 | B322: BAUTISTA | C322: CARLO | E322: 67978 | F322: 29209 | G322: M | H322: carloabautista@yahoo.com
A323: 3405-00 | B323: DIMAYUGA | C323: CARLO ANTONIO | E323: 80187 | F323: 26701 | G323: M | H323: carlodimayuga@yahoo.com
A324: 8514-00 | B324: GONZALEZ | C324: CARLO | F324: 32380 | G324: M | H324: carlog_25@yahoo.com
A325: 8444-01 | B325: ROMAN | C325: CARLO JOSEPH | E325: 1000419 | F325: 32585 | G325: M | H325: carlojroman@gmail.com
A326: 8118-00 | B326: JOAQUIN | C326: CARLOS "JACK" | E326: 75421 | F326: 18237 | G326: M | H326: carlosjoaquin012@gmail.com
A327: 3408-03 | B327: LIMPO | C327: JUAN CARLOS | E327: 1005081 | F327: 37904 | G327: M | H327: carloslimpo48@gmail.com
A328: 8568-00 | B328: CERVANTES | C328: CARLOS RHEAL | E328: 16101 | F328: 24562 | G328: M | H328: carlosrheal.crc@gmail.com
...

Sheet EMAIL
A1: ACCTNO | B1: NAME | C1: EMAIL
A2: 2585-00 | B2: BENG CHEONG TAY | C2: petertay29@gmail.com
A3: 2688-02 | B3: ERIC JOHN ILLESCAS | C3: 268802@noemail.com
A4: 8487-01 | B4: MANUEL RAVAGO | C4: mjravago@outlook.com
A5: 8453-02 | B5: KEIRA IZABELLE S. LIM | C5: keira@noemail.com
A6: 8194-02 | B6: TAMARA JORGE | C6: jorge.tamara@gmail.com
A7: 3466-00 | B7: WILLIAM LESTER KHO | C7: williamkho1@yahoo.com
A8: 0138-00 | B8: JAIME LIM SE CHUN | C8: jaimesclim@hotmail.com
A9: 8495-00 | B9: JOHANN LESTER SY | C9: johannsy1998@gmail.com
A10: 3417-00 | B10: VICTORIO EMMANUEL DIONISIO | C10: dinomdionisio@gmail.com
A11: 8285-00 | B11: MIGUEL B. MORADA JR. | C11: mmjr100@icloud.com
A12: 3459-01 | B12: ARLENE ANG | C12: arlene@conmaster.com.ph
... A3322: 7042-04 | B3322: VITTO MIRAVITE | C3322: vittomiravite96@gmail.com
